Workbook
Name Annual_Periods: OFFSET(Financials!$E$6,0,1):OFFSET(Financials!$O$6,0,-1)
Name BS_End: Financials!$B$98
Name BS_Start: Financials!$B$49
Name Comp_Name: Assumptions!$B$2
Name Cost_of_Debt: Assumptions!$B$15
Name Cost_of_Equity: Assumptions!$B$22
Name Country_RP: Assumptions!$B$19
Name Current_Price: Assumptions!$B$4
Name DCF_Enterprise_Value: 'DCF (H-Model for TV)'!$C$55
Name DCF_Enterprise_Value: DCF!$C$52
Name DCF_Enterprise_Value_PerShare: 'DCF (H-Model for TV)'!$D$55
Name DCF_Enterprise_Value_PerShare: DCF!$D$52
Name DCF_Equity_Value: 'DCF (H-Model for TV)'!$C$57
Name DCF_Equity_Value: DCF!$C$54
Name DCF_Equity_Value_PerShare: 'DCF (H-Model for TV)'!$D$57
Name DCF_Equity_Value_PerShare: DCF!$D$54
Name Debt_Adj_Factor: Assumptions!$B$13
Name Debt_MV: Assumptions!$B$28
Name Equity_Beta: Assumptions!$B$21
Name Equity_MV: Assumptions!$B$27
Name Equity_Risk_Premium: Assumptions!$B$18
Name Risk_Free_Rate: Assumptions!$B$12
Name Scale_Symbol: Assumptions!$D$6
Name Scaler: Assumptions!$C$6
Name Shares_Out: Assumptions!$B$25
Name Size_RP: Assumptions!$B$20
Name Tax_Rate: Assumptions!$B$14
Name Terminal_Rate: Assumptions!$B$33
Name Total_Capitalization: Assumptions!$B$29
Name WACC: Assumptions!$C$30
Name WACC_Override: 'DCF (H-Model for TV)'!$L$27
Name WACC_Override: DCF!$L$27

Sheet Valuation-->
A1: General Guidelines
A3: 1) | B3: Use all in-cell notes where possible. They are intended to be helpful.
A4: 2) | B4: Color coding is important Excel modeling practice:
B5: Purple = Historical Data
B6: Blue = Assumptions & Projections
B7: Black = Formulas
B8: Green = Links to Other Sheets
B9: User Input Cells
A18: 360 Huntington Fund Valuation Template
A19: Version: Spring 2024 Update
A20: By: Sumukh

Sheet PB_CACHE
A1: H4sIAAAAAAAEAM2QQUvDMBTHu1Wxoh8id0toa+fcoRerKLjDpMXLGDMNDxuWJjVJhe5j+IU1KZ0ePHj1BfJeAv/f+/P3Jp7nfdpy3dX51F5PK2ZofSPlDpV9CxotWaWI6kP0DEozKbIkShKc4hhHIco7bjoFmYDOKMJDtOoqzugj9KXcgchEx/mx4xff2O2A3Y5YXIBihLM9qTjkhNbw++eilO0S3oEPr1tGjbVhtb7lnoyuglw2LVGgggei64LtwfO94GNS9NpAg3PJOQw6je9B2A300O/eOrvN9AfAS7xej6rCKCZeQ9RoKhVn1U8GKY7c+TuAaj4nMzq7iheXKUTXi80mmI5xn/rjcOSG/2jVmTv7At67jZonAgAA

Sheet Summary
C3: =Comp_Name -> Nu Scale | D3: | Per Share Valuation Summary
B19: Models
B21: Valuation Methodology | E21: Low (-10%) | F21: Median | G21: High (+10%) | H21: Weights | J21: Baseline Metrics ($B): | K21: =DCF!$E$31 -> 46022 | L21: Per Share
B22: Discounted Cash Flow (Exit Multiple) | E22: =IFERROR(F22*0.9,"--") -> 126.62037 | F22: ='DCF (H-Model for TV)'!DCF_Equity_Value_PerShare -> 140.6893 | G22: =IFERROR(F22*1.1,"--") -> 154.75823 | H22: 0.15 | J22: Revenue | K22: =INDEX(Financials!$11:$11,MATCH(K$21,Financials!$6:$6,0))*Scaler/(10^9) -> 0.051863 | L22: =K22/Shares_Out*(10^9)/Scaler -> 0.38735529
B23: Market Multiples: EV to Sales | E23: =IFERROR(F23*0.9,"--") -> 38.951435 | F23: =IFERROR('EV-Sales Multiples'!$D$36,"--") -> 43.279372 | G23: =IFERROR(F23*1.1,"--") -> 47.60731 | H23: 0.45 | J23: Gross Margin | K23: =INDEX(Financials!$17:$17,MATCH(K$21,Financials!$6:$6,0))*Scaler/(10^9) -> 0.0414904 | L23: =K23/Shares_Out*(10^9)/Scaler -> 0.30988423
B24: Market Multiples: Market Cap to Sales | E24: =IFERROR(F24*0.9,"--") -> 35.082823 | F24: =IFERROR('Market Cap-Sales Multiples'!D36,"--") -> 38.980915 | G24: =IFERROR(F24*1.1,"--") -> 42.879006 | H24: 0.4 | J24: Operating Income | K24: =INDEX(Financials!$24:$24,MATCH(K$21,Financials!$6:$6,0))*Scaler/(10^9) -> -0.13743695 | L24: =K24/Shares_Out*(10^9)/Scaler -> -1.0264915
B25: Target Price (12-Month) | E25: =SUMPRODUCT(E22:E24,$H$22:$H$24) -> 50.554331 | F25: =SUMPRODUCT(F22:F24,$H$22:$H$24) -> 56.171479 | G25: =SUMPRODUCT(G22:G24,$H$22:$H$24) -> 61.788627 | H25: =SUM(H22:H24) -> 1 | J25: Net Income | K25: =INDEX(Financials!$40:$40,MATCH(K$21,Financials!$6:$6,0))*Scaler/(10^9) -> -0.13743695 | L25: =K25/Shares_Out*(10^9)/Scaler -> -1.0264915
B27: Current Price | F27: =Current_Price -> 44.25
B28: Upside from Current Price (12 Month) | F28: =F25/F27-1 -> 0.26941195
B29: Expected Alpha (12 Month) | F29: =F28-Cost_of_Equity -> 0.095207954
B31: Graph Options -- Do Not Change!
D32: Low | E32: Median | F32: Extra | G32: High | H32: EV
B33: =B22&" "&TEXT(H22,"(0%)") -> Discounted Cash Flow (Exit Multiple) (15%) | D33: =E22 -> 126.62037 | E33: =IFERROR(F22-D33,"NA") -> 14.06893 | F33: =0.025*$F$25 -> 1.404287 | G33: =IFERROR(G22-D33-E33-F33,"NA") -> 12.664643 | H33: =$F$25 -> 56.171479
B34: =#REF!&" "&TEXT(#REF!,"(0%)") -> #REF! | D34: =#REF! -> #REF! | E34: =IFERROR(#REF!-D34,"NA") -> NA | F34: =F$33 -> 1.404287 | G34: =IFERROR(#REF!-D34-E34-F34,"NA") -> NA | H34: =$F$25 -> 56.171479
B35: =B23&" "&TEXT(H23,"(0%)") -> Market Multiples: EV to Sales (45%) | D35: =E23 -> 38.951435 | E35: =IFERROR(F23-D35,"NA") -> 4.3279372 | F35: =F$33 -> 1.404287 | G35: =IFERROR(G23-D35-E35-F35,"NA") -> 2.9236503 | H35: =$F$25 -> 56.171479
B36: =B24&" "&TEXT(H24,"(0%)") -> Market Multiples: Market Cap to Sales (40%) | D36: =E24 -> 35.082823 | E36: =IFERROR(F24-D36,"NA") -> 3.8980915 | F36: =F$33 -> 1.404287 | G36: =IFERROR(G24-D36-E36-F36,"NA") -> 2.4938045 | H36: =$F$25 -> 56.171479

Sheet Assumptions
A1: General Information:
A2: Entity Name | B2: Nu Scale
A3: Ticker Symbol (for Excel API) | B3: #VALUE!
A4: Current Share Price | B4: {=_FV(B3,"Price")} -> 44.25
A5: Currency | B5: USD
A6: Numeral Scaling | B6: Thousands | C6: =IF(B6="",1,IF(B6="Thousands",(10^3),IF(B6="Millions",(10^6),IF(B6="Billions",(10^9))))) -> 1000 | D6: =IF(B6="","Actual",IF(B6="Thousands","K",IF(B6="Millions","M",IF(B6="Billions","B")))) -> K | E6: For the numeral system to work please divide with "decimal" (cell highlighted in blue) while adding values
A7: Start Period | B7: 44560
A9: Cost of Capital Assumptions
A11: Cost of Debt
A12: Risk-Free Rate (10 Year T-Bill) | B12: 0.0409
A13: Debt Adjustment Factor | B13: 1.38
A14: Assumed Effective Tax Rate | B14: 0.1737
A15: After-Tax Cost of Debt | B15: =(Risk_Free_Rate*Debt_Adj_Factor)*(1-Tax_Rate) -> 0.046638025
A17: Cost of Equity
A18: Equity Risk Premium | B18: 0.07 | D18: Equity Risk Premium (S&P 500 US)
A19: Country Risk Premium | B19: 0.006 | D19: Country Risk Premium
A20: Size Risk Premium | B20: 0 | D20: Size Risk Premium
A21: Company Equity Beta | B21: 1.754 | D21: Industry Betas
A22: CAPM Cost of Equity | B22: =(Equity_Beta*(Equity_Risk_Premium+Country_RP))+Risk_Free_Rate+Size_RP -> 0.174204
A24: Company Capitalization & WACC
A25: ="Equity Shares Outstanding ("&Scale_Symbol&")" -> Equity Shares Outstanding (K) | B25: 133890
A26: ="Company Capitalization ($"&Scale_Symbol&")" -> Company Capitalization ($K)
A27: Market Value of Equity | B27: =Current_Price*Shares_Out -> 5924632.5 | C27: =Equity_MV/Total_Capitalization -> 1
A28: Market Value of Debt | B28: 0 | C28: =Debt_MV/Total_Capitalization -> 0
A29: Total Capitalization | B29: =B27+B28 -> 5924632.5 | C29: =C27+C28 -> 1
A30: WACC | C30: =(C27*Cost_of_Equity)+(C28*Cost_of_Debt) -> 0.174204
A32: Sentivity Matrix | B32: Normal | C32: Lower | D32: Higher
A33: Perpetuity Growth Rate | B33: 0.02 | C33: =$B$33+C34 -> 0.015 | D33: =$B$33+D34 -> 0.025
A34: ∆ (+/-) in Perpetuity Growth Rate | C34: -0.005 | D34: 0.005
A35: WACC Range | B35: =WACC -> 0.174204 | C35: =$B$35+C36 -> 0.164204 | D35: =$B$35+D36 -> 0.184204
A36: ∆ (+/-) WACC | C36: -0.01 | D36: 0.01

Sheet Financials
D3: 360 Huntington Fund Free Cash Flow Model | F3: Historical | J3: Projected | P3: Common Size | Z3: Key Assumptions
D6: TTM based on: | F6: =Assumptions!$B$7 -> 44560 | G6: =EOMONTH(OFFSET(G$6,0,-1),12) -> 44926 | H6: =EOMONTH(OFFSET(H$6,0,-1),12) -> 45291 | I6: =EOMONTH(OFFSET(I$6,0,-1),12) -> 45657 | J6: =EOMONTH(OFFSET(J$6,0,-1),12) -> 46022 | K6: =EOMONTH(OFFSET(K$6,0,-1),12) -> 46387 | L6: =EOMONTH(OFFSET(L$6,0,-1),12) -> 46752 | M6: =EOMONTH(OFFSET(M$6,0,-1),12) -> 47118 | N6: =EOMONTH(OFFSET(N$6,0,-1),12) -> 47483 | P6: {=Annual_Periods} -> 44560 | Q6: 44926 | R6: 45291 | S6: 45657 | T6: 46022 | U6: 46387 | V6: 46752 | W6: 47118 | X6: 47483 | Z6: {=INDEX(Annual_Periods,MATCH("Projected",$F$3:$N$3,))} -> 46022 | AA6: =EOMONTH(OFFSET(AA$6,0,-1),12) -> 46387 | AB6: =EOMONTH(OFFSET(AB$6,0,-1),12) -> 46752 | AC6: =EOMONTH(OFFSET(AC$6,0,-1),12) -> 47118 | AD6: =EOMONTH(OFFSET(AD$6,0,-1),12) -> 47483
A8: X | D8: Consolidated Income Statement
D9: Revenues
D10: Sales & Services Revenue | F10: 2862 | G10: 11804 | H10: 22810 | I10: 37045 | J10: =I10*(1+Z10) -> 51863 | K10: =J10*(1+AA10) -> 82980.8 | L10: =K10*(1+AB10) -> 165961.6 | M10: =L10*(1+AC10) -> 365115.52 | N10: =M10*(1+AD10) -> 657207.94 | Z10: 0.4 | AA10: 0.6 | AB10: 1 | AC10: 1.2 | AD10: 0.8
D11: Total Net Revenue | F11: =SUBTOTAL(9,OFFSET(F9,1,0):OFFSET(F11,-1,0)) -> 2862 | G11: =SUBTOTAL(9,OFFSET(G9,1,0):OFFSET(G11,-1,0)) -> 11804 | H11: =SUBTOTAL(9,OFFSET(H9,1,0):OFFSET(H11,-1,0)) -> 22810 | I11: =SUBTOTAL(9,OFFSET(I9,1,0):OFFSET(I11,-1,0)) -> 37045 | J11: =SUBTOTAL(9,OFFSET(J9,1,0):OFFSET(J11,-1,0)) -> 51863 | K11: =SUBTOTAL(9,OFFSET(K9,1,0):OFFSET(K11,-1,0)) -> 82980.8 | L11: =SUBTOTAL(9,OFFSET(L9,1,0):OFFSET(L11,-1,0)) -> 165961.6 | M11: =SUBTOTAL(9,OFFSET(M9,1,0):OFFSET(M11,-1,0)) -> 365115.52 | N11: =SUBTOTAL(9,OFFSET(N9,1,0):OFFSET(N11,-1,0)) -> 657207.94 | P11: {=IFERROR(ABS(OFFSET($E$6,ROW()-ROW(Annual_Periods),MATCH(P$6,Annual_Periods,0)) / OFFSET($E$11,0,MATCH(P$6,Annual_Periods,0))),"NA")} -> 1 | Q11: {=IFERROR(ABS(OFFSET($E$6,ROW()-ROW(Annual_Periods),MATCH(Q$6,Annual_Periods,0)) / OFFSET($E$11,0,MATCH(Q$6,Annual_Periods,0))),"NA")} -> 1 | R11: {=IFERROR(ABS(OFFSET($E$6,ROW()-ROW(Annual_Periods),MATCH(R$6,Annual_Periods,0)) / OFFSET($E$11,0,MATCH(R$6,Annual_Periods,0))),"NA")} -> 1 | S11: {=IFERROR(ABS(OFFSET($E$6,ROW()-ROW(Annual_Periods),MATCH(S$6,Annual_Periods,0)) / OFFSET($E$11,0,MATCH(S$6,Annual_Periods,0))),"NA")} -> 1 | T11: {=IFERROR(ABS(OFFSET($E$6,ROW()-ROW(Annual_Periods),MATCH(T$6,Annual_Periods,0)) / OFFSET($E$11,0,MATCH(T$6,Annual_Periods,0))),"NA")} -> 1 | U11: {=IFERROR(ABS(OFFSET($E$6,ROW()-ROW(Annual_Periods),MATCH(U$6,Annual_Periods,0)) / OFFSET($E$11,0,MATCH(U$6,Annual_Periods,0))),"NA")} -> 1 | V11: {=IFERROR(ABS(OFFSET($E$6,ROW()-ROW(Annual_Periods),MATCH(V$6,Annual_Periods,0)) / OFFSET($E$11,0,MATCH(V$6,Annual_Periods,0))),"NA")} -> 1 | W11: {=IFERROR(ABS(OFFSET($E$6,ROW()-ROW(Annual_Periods),MATCH(W$6,Annual_Periods,0)) / OFFSET($E$11,0,MATCH(W$6,Annual_Periods,0))),"NA")} -> 1 | X11: {=IFERROR(ABS(OFFSET($E$6,ROW()-ROW(Annual_Periods),MATCH(X$6,Annual_Periods,0)) / OFFSET($E$11,0,MATCH(X$6,Annual_Periods,0))),"NA")} -> 1 | AE11: CAGR | AF11: =(N11/I11)^(1/5) - 1 -> 0.77743873
D12: Net Revenue Growth % | F12: =IFERROR(F11/OFFSET(F11,0,-1)-1,"NA") -> NA | G12: =IFERROR(G11/OFFSET(G11,0,-1)-1,"NA") -> 3.1243885 | H12: =IFERROR(H11/OFFSET(H11,0,-1)-1,"NA") -> 0.9323958 | I12: =IFERROR(I11/OFFSET(I11,0,-1)-1,"NA") -> 0.62406839 | J12: =IFERROR(J11/OFFSET(J11,0,-1)-1,"NA") -> 0.4 | K12: =IFERROR(K11/OFFSET(K11,0,-1)-1,"NA") -> 0.6 | L12: =IFERROR(L11/OFFSET(L11,0,-1)-1,"NA") -> 1 | M12: =IFERROR(M11/OFFSET(M11,0,-1)-1,"NA") -> 1.2 | N12: =IFERROR(N11/OFFSET(N11,0,-1)-1,"NA") -> 0.8
D14: COGS (Enter as Negative)
D15: Cost of Goods & Services | F15: -1770 | G15: -7317 | H15: -18961 | I15: -4937 | J15: =-J$11*(Z15) -> -10372.6 | K15: =-K$11*(AA15) -> -20745.2 | L15: =-L$11*(AB15) -> -41490.4 | M15: =-M$11*(AC15) -> -109534.66 | N15: =-N$11*(AD15) -> -230022.78 | P15: {=IFERROR(ABS(OFFSET($E$6,ROW()-ROW(Annual_Periods),MATCH(P$6,Annual_Periods,0)) / OFFSET($E$11,0,MATCH(P$6,Annual_Periods,0))),"NA")} -> 0.61844864 | Q15: {=IFERROR(ABS(OFFSET($E$6,ROW()-ROW(Annual_Periods),MATCH(Q$6,Annual_Periods,0)) / OFFSET($E$11,0,MATCH(Q$6,Annual_Periods,0))),"NA")} -> 0.61987462 | R15: {=IFERROR(ABS(OFFSET($E$6,ROW()-ROW(Annual_Periods),MATCH(R$6,Annual_Periods,0)) / OFFSET($E$11,0,MATCH(R$6,Annual_Periods,0))),"NA")} -> 0.83125822 | S15: {=IFERROR(ABS(OFFSET($E$6,ROW()-ROW(Annual_Periods),MATCH(S$6,Annual_Periods,0)) / OFFSET($E$11,0,MATCH(S$6,Annual_Periods,0))),"NA")} -> 0.13327035 | T15: {=IFERROR(ABS(OFFSET($E$6,ROW()-ROW(Annual_Periods),MATCH(T$6,Annual_Periods,0)) / OFFSET($E$11,0,MATCH(T$6,Annual_Periods,0))),"NA")} -> 0.2 | U15: {=IFERROR(ABS(OFFSET($E$6,ROW()-ROW(Annual_Periods),MATCH(U$6,Annual_Periods,0)) / OFFSET($E$11,0,MATCH(U$6,Annual_Periods,0))),"NA")} -> 0.25 | V15: {=IFERROR(ABS(OFFSET($E$6,ROW()-ROW(Annual_Periods),MATCH(V$6,Annual_Periods,0)) / OFFSET($E$11,0,MATCH(V$6,Annual_Periods,0))),"NA")} -> 0.25 | W15: {=IFERROR(ABS(OFFSET($E$6,ROW()-ROW(Annual_Periods),MATCH(W$6,Annual_Periods,0)) / OFFSET($E$11,0,MATCH(W$6,Annual_Periods,0))),"NA")} -> 0.3 | X15: {=IFERROR(ABS(OFFSET($E$6,ROW()-ROW(Annual_Periods),MATCH(X$6,Annual_Periods,0)) / OFFSET($E$11,0,MATCH(X$6,Annual_Periods,0))),"NA")} -> 0.35 | Z15: 0.2 | AA15: 0.25 | AB15: 0.25 | AC15: 0.3 | AD15: 0.35
D16: Total COGS | F16: =SUBTOTAL(9,OFFSET(F14,1,0):OFFSET(F16,-1,0)) -> -1770 | G16: =SUBTOTAL(9,OFFSET(G14,1,0):OFFSET(G16,-1,0)) -> -7317 | H16: =SUBTOTAL(9,OFFSET(H14,1,0):OFFSET(H16,-1,0)) -> -18961 | I16: =SUBTOTAL(9,OFFSET(I14,1,0):OFFSET(I16,-1,0)) -> -4937 | J16: =SUBTOTAL(9,OFFSET(J14,1,0):OFFSET(J16,-1,0)) -> -10372.6 | K16: =SUBTOTAL(9,OFFSET(K14,1,0):OFFSET(K16,-1,0)) -> -20745.2 | L16: =SUBTOTAL(9,OFFSET(L14,1,0):OFFSET(L16,-1,0)) -> -41490.4 | M16: =SUBTOTAL(9,OFFSET(M14,1,0):OFFSET(M16,-1,0)) -> -109534.66 | N16: =SUBTOTAL(9,OFFSET(N14,1,0):OFFSET(N16,-1,0)) -> -230022.78 | P16: {=IFERROR(ABS(OFFSET($E$6,ROW()-ROW(Annual_Periods),MATCH(P$6,Annual_Periods,0)) / OFFSET($E$11,0,MATCH(P$6,Annual_Periods,0))),"NA")} -> 0.61844864 | Q16: {=IFERROR(ABS(OFFSET($E$6,ROW()-ROW(Annual_Periods),MATCH(Q$6,Annual_Periods,0)) / OFFSET($E$11,0,MATCH(Q$6,Annual_Periods,0))),"NA")} -> 0.61987462 | R16: {=IFERROR(ABS(OFFSET($E$6,ROW()-ROW(Annual_Periods),MATCH(R$6,Annual_Periods,0)) / OFFSET($E$11,0,MATCH(R$6,Annual_Periods,0))),"NA")} -> 0.83125822 | S16: {=IFERROR(ABS(OFFSET($E$6,ROW()-ROW(Annual_Periods),MATCH(S$6,Annual_Periods,0)) / OFFSET($E$11,0,MATCH(S$6,Annual_Periods,0))),"NA")} -> 0.13327035 | T16: {=IFERROR(ABS(OFFSET($E$6,ROW()-ROW(Annual_Periods),MATCH(T$6,Annual_Periods,0)) / OFFSET($E$11,0,MATCH(T$6,Annual_Periods,0))),"NA")} -> 0.2 | U16: {=IFERROR(ABS(OFFSET($E$6,ROW()-ROW(Annual_Periods),MATCH(U$6,Annual_Periods,0)) / OFFSET($E$11,0,MATCH(U$6,Annual_Periods,0))),"NA")} -> 0.25 | V16: {=IFERROR(ABS(OFFSET($E$6,ROW()-ROW(Annual_Periods),MATCH(V$6,Annual_Periods,0)) / OFFSET($E$11,0,MATCH(V$6,Annual_Periods,0))),"NA")} -> 0.25 | W16: {=IFERROR(ABS(OFFSET($E$6,ROW()-ROW(Annual_Periods),MATCH(W$6,Annual_Periods,0)) / OFFSET($E$11,0,MATCH(W$6,Annual_Periods,0))),"NA")} -> 0.3 | X16: {=IFERROR(ABS(OFFSET($E$6,ROW()-ROW(Annual_Periods),MATCH(X$6,Annual_Periods,0)) / OFFSET($E$11,0,MATCH(X$6,Annual_Periods,0))),"NA")} -> 0.35 | AE16: Avg COGS% of Sales | AF16: =AVERAGE(T16:X16) -> 0.27
D17: Gross Profit | F17: =F11+F16 -> 1092 | G17: =G11+G16 -> 4487 | H17: =H11+H16 -> 3849 | I17: =I11+I16 -> 32108 | J17: =J11+J16 -> 41490.4 | K17: =K11+K16 -> 62235.6 | L17: =L11+L16 -> 124471.2 | M17: =M11+M16 -> 255580.86 | N17: =N11+N16 -> 427185.16 | P17: {=IFERROR(OFFSET($E$6,ROW()-ROW(Annual_Periods),MATCH(P$6,Annual_Periods,0)) / OFFSET($E$11,0,MATCH(P$6,Annual_Periods,0)),"NA")} -> 0.38155136 | Q17: {=IFERROR(OFFSET($E$6,ROW()-ROW(Annual_Periods),MATCH(Q$6,Annual_Periods,0)) / OFFSET($E$11,0,MATCH(Q$6,Annual_Periods,0)),"NA")} -> 0.38012538 | R17: {=IFERROR(OFFSET($E$6,ROW()-ROW(Annual_Periods),MATCH(R$6,Annual_Periods,0)) / OFFSET($E$11,0,MATCH(R$6,Annual_Periods,0)),"NA")} -> 0.16874178 | S17: {=IFERROR(OFFSET($E$6,ROW()-ROW(Annual_Periods),MATCH(S$6,Annual_Periods,0)) / OFFSET($E$11,0,MATCH(S$6,Annual_Periods,0)),"NA")} -> 0.86672965 | T17: {=IFERROR(OFFSET($E$6,ROW()-ROW(Annual_Periods),MATCH(T$6,Annual_Periods,0)) / OFFSET($E$11,0,MATCH(T$6,Annual_Periods,0)),"NA")} -> 0.8 | U17: {=IFERROR(OFFSET($E$6,ROW()-ROW(Annual_Periods),MATCH(U$6,Annual_Periods,0)) / OFFSET($E$11,0,MATCH(U$6,Annual_Periods,0)),"NA")} -> 0.75 | V17: {=IFERROR(OFFSET($E$6,ROW()-ROW(Annual_Periods),MATCH(V$6,Annual_Periods,0)) / OFFSET($E$11,0,MATCH(V$6,Annual_Periods,0)),"NA")} -> 0.75 | W17: {=IFERROR(OFFSET($E$6,ROW()-ROW(Annual_Periods),MATCH(W$6,Annual_Periods,0)) / OFFSET($E$11,0,MATCH(W$6,Annual_Periods,0)),"NA")} -> 0.7 | X17: {=IFERROR(OFFSET($E$6,ROW()-ROW(Annual_Periods),MATCH(X$6,Annual_Periods,0)) / OFFSET($E$11,0,MATCH(X$6,Annual_Periods,0)),"NA")} -> 0.65
D18: Total Gross Margin % | F18: =IFERROR(F17/F$11,"NA") -> 0.38155136 | G18: =IFERROR(G17/G$11,"NA") -> 0.38012538 | H18: =IFERROR(H17/H$11,"NA") -> 0.16874178 | I18: =IFERROR(I17/I$11,"NA") -> 0.86672965 | J18: =IFERROR(J17/J$11,"NA") -> 0.8 | K18: =IFERROR(K17/K$11,"NA") -> 0.75 | L18: =IFERROR(L17/L$11,"NA") -> 0.75 | M18: =IFERROR(M17/M$11,"NA") -> 0.7 | N18: =IFERROR(N17/N$11,"NA") -> 0.65
D20: Operating Expenses (Enter as Positive)
D21: SG&A | F21: 45226 | G21: 55307 | H21: 65404 | I21: 75901 | J21: =J$11*(Z21) -> 88167.1 | K21: =K$11*(AA21) -> 95427.92 | L21: =L$11*(AB21) -> 99576.96 | M21: =M$11*(AC21) -> 109534.66 | N21: =N$11*(AD21) -> 177446.14 | P21: {=IFERROR(ABS(OFFSET($E$6,ROW()-ROW(Annual_Periods),MATCH(P$6,Annual_Periods,0)) / OFFSET($E$11,0,MATCH(P$6,Annual_Periods,0))),"NA")} -> 15.802236 | Q21: {=IFERROR(ABS(OFFSET($E$6,ROW()-ROW(Annual_Periods),MATCH(Q$6,Annual_Periods,0)) / OFFSET($E$11,0,MATCH(Q$6,Annual_Periods,0))),"NA")} -> 4.6854456 | R21: {=IFERROR(ABS(OFFSET($E$6,ROW()-ROW(Annual_Periods),MATCH(R$6,Annual_Periods,0)) / OFFSET($E$11,0,MATCH(R$6,Annual_Periods,0))),"NA")} -> 2.8673389 | S21: {=IFERROR(ABS(OFFSET($E$6,ROW()-ROW(Annual_Periods),MATCH(S$6,Annual_Periods,0)) / OFFSET($E$11,0,MATCH(S$6,Annual_Periods,0))),"NA")} -> 2.0488865 | T21: {=IFERROR(ABS(OFFSET($E$6,ROW()-ROW(Annual_Periods),MATCH(T$6,Annual_Periods,0)) / OFFSET($E$11,0,MATCH(T$6,Annual_Periods,0))),"NA")} -> 1.7 | U21: {=IFERROR(ABS(OFFSET($E$6,ROW()-ROW(Annual_Periods),MATCH(U$6,Annual_Periods,0)) / OFFSET($E$11,0,MATCH(U$6,Annual_Periods,0))),"NA")} -> 1.15 | V21: {=IFERROR(ABS(OFFSET($E$6,ROW()-ROW(Annual_Periods),MATCH(V$6,Annual_Periods,0)) / OFFSET($E$11,0,MATCH(V$6,Annual_Periods,0))),"NA")} -> 0.6 | W21: {=IFERROR(ABS(OFFSET($E$6,ROW()-ROW(Annual_Periods),MATCH(W$6,Annual_Periods,0)) / OFFSET($E$11,0,MATCH(W$6,Annual_Periods,0))),"NA")} -> 0.3 | X21: {=IFERROR(ABS(OFFSET($E$6,ROW()-ROW(Annual_Periods),MATCH(X$6,Annual_Periods,0)) / OFFSET($E$11,0,MATCH(X$6,Annual_Periods,0))),"NA")} -> 0.27 | Z21: 1.7 | AA21: 1.15 | AB21: 0.6 | AC21: 0.3 | AD21: 0.27
D22: R&D | F22: 93136 | G22: 127662 | H22: 156050 | I22: 46817 | J22: =J$11*(Z22) -> 49269.85 | K22: =K$11*(AA22) -> 45639.44 | L22: =L$11*(AB22) -> 41490.4 | M22: =M$11*(AC22) -> 36511.552 | N22: =N$11*(AD22) -> 39432.476 | P22: {=IFERROR(ABS(OFFSET($E$6,ROW()-ROW(Annual_Periods),MATCH(P$6,Annual_Periods,0)) / OFFSET($E$11,0,MATCH(P$6,Annual_Periods,0))),"NA")} -> 32.542278 | Q22: {=IFERROR(ABS(OFFSET($E$6,ROW()-ROW(Annual_Periods),MATCH(Q$6,Annual_Periods,0)) / OFFSET($E$11,0,MATCH(Q$6,Annual_Periods,0))),"NA")} -> 10.815147 | R22: {=IFERROR(ABS(OFFSET($E$6,ROW()-ROW(Annual_Periods),MATCH(R$6,Annual_Periods,0)) / OFFSET($E$11,0,MATCH(R$6,Annual_Periods,0))),"NA")} -> 6.8412977 | S22: {=IFERROR(ABS(OFFSET($E$6,ROW()-ROW(Annual_Periods),MATCH(S$6,Annual_Periods,0)) / OFFSET($E$11,0,MATCH(S$6,Annual_Periods,0))),"NA")} -> 1.2637873 | T22: {=IFERROR(ABS(OFFSET($E$6,ROW()-ROW(Annual_Periods),MATCH(T$6,Annual_Periods,0)) / OFFSET($E$11,0,MATCH(T$6,Annual_Periods,0))),"NA")} -> 0.95 | U22: {=IFERROR(ABS(OFFSET($E$6,ROW()-ROW(Annual_Periods),MATCH(U$6,Annual_Periods,0)) / OFFSET($E$11,0,MATCH(U$6,Annual_Periods,0))),"NA")} -> 0.55 | V22: {=IFERROR(ABS(OFFSET($E$6,ROW()-ROW(Annual_Periods),MATCH(V$6,Annual_Periods,0)) / OFFSET($E$11,0,MATCH(V$6,Annual_Periods,0))),"NA")} -> 0.25 | W22: {=IFERROR(ABS(OFFSET($E$6,ROW()-ROW(Annual_Periods),MATCH(W$6,Annual_Periods,0)) / OFFSET($E$11,0,MATCH(W$6,Annual_Periods,0))),"NA")} -> 0.1 | X22: {=IFERROR(ABS(OFFSET($E$6,ROW()-ROW(Annual_Periods),MATCH(X$6,Annual_Periods,0)) / OFFSET($E$11,0,MATCH(X$6,Annual_Periods,0))),"NA")} -> 0.06 | Z22: 0.95 | AA22: 0.55 | AB22: 0.25 | AC22: 0.1 | AD22: 0.06
D23: Other Operating Expenses | F23: 37030 | G23: 51513 | H23: 57960 | I23: 48115 | J23: =J$11*(Z23) -> 41490.4 | K23: =K$11*(AA23) -> 45639.44 | L23: =L$11*(AB23) -> 49788.48 | M23: =M$11*(AC23) -> 51116.173 | N23: =N$11*(AD23) -> 78864.952 | P23: {=IFERROR(ABS(OFFSET($E$6,ROW()-ROW(Annual_Periods),MATCH(P$6,Annual_Periods,0)) / OFFSET($E$11,0,MATCH(P$6,Annual_Periods,0))),"NA")} -> 12.938505 | Q23: {=IFERROR(ABS(OFFSET($E$6,ROW()-ROW(Annual_Periods),MATCH(Q$6,Annual_Periods,0)) / OFFSET($E$11,0,MATCH(Q$6,Annual_Periods,0))),"NA")} -> 4.3640291 | R23: {=IFERROR(ABS(OFFSET($E$6,ROW()-ROW(Annual_Periods),MATCH(R$6,Annual_Periods,0)) / OFFSET($E$11,0,MATCH(R$6,Annual_Periods,0))),"NA")} -> 2.5409908 | S23: {=IFERROR(ABS(OFFSET($E$6,ROW()-ROW(Annual_Periods),MATCH(S$6,Annual_Periods,0)) / OFFSET($E$11,0,MATCH(S$6,Annual_Periods,0))),"NA")} -> 1.2988258 | T23: {=IFERROR(ABS(OFFSET($E$6,ROW()-ROW(Annual_Periods),MATCH(T$6,Annual_Periods,0)) / OFFSET($E$11,0,MATCH(T$6,Annual_Periods,0))),"NA")} -> 0.8 | U23: {=IFERROR(ABS(OFFSET($E$6,ROW()-ROW(Annual_Periods),MATCH(U$6,Annual_Periods,0)) / OFFSET($E$11,0,MATCH(U$6,Annual_Periods,0))),"NA")} -> 0.55 | V23: {=IFERROR(ABS(OFFSET($E$6,ROW()-ROW(Annual_Periods),MATCH(V$6,Annual_Periods,0)) / OFFSET($E$11,0,MATCH(V$6,Annual_Periods,0))),"NA")} -> 0.3 | W23: {=IFERROR(ABS(OFFSET($E$6,ROW()-ROW(Annual_Periods),MATCH(W$6,Annual_Periods,0)) / OFFSET($E$11,0,MATCH(W$6,Annual_Periods,0))),"NA")} -> 0.14 | X23: {=IFERROR(ABS(OFFSET($E$6,ROW()-ROW(Annual_Periods),MATCH(X$6,Annual_Periods,0)) / OFFSET($E$11,0,MATCH(X$6,Annual_Periods,0))),"NA")} -> 0.12 | Z23: 0.8 | AA23: 0.55 | AB23: 0.3 | AC23: 0.14 | AD23: 0.12
D24: Operating Income (EBIT) | F24: =F17-SUBTOTAL(9,OFFSET(F20,1,0):OFFSET(F24,-1,0)) -> -174300 | G24: =G17-SUBTOTAL(9,OFFSET(G20,1,0):OFFSET(G24,-1,0)) -> -229995 | H24: =H17-SUBTOTAL(9,OFFSET(H20,1,0):OFFSET(H24,-1,0)) -> -275565 | I24: =I17-SUBTOTAL(9,OFFSET(I20,1,0):OFFSET(I24,-1,0)) -> -138725 | J24: =J17-SUBTOTAL(9,OFFSET(J20,1,0):OFFSET(J24,-1,0)) -> -137436.95 | K24: =K17-SUBTOTAL(9,OFFSET(K20,1,0):OFFSET(K24,-1,0)) -> -124471.2 | L24: =L17-SUBTOTAL(9,OFFSET(L20,1,0):OFFSET(L24,-1,0)) -> -66384.64 | M24: =M17-SUBTOTAL(9,OFFSET(M20,1,0):OFFSET(M24,-1,0)) -> 58418.483 | N24: =N17-SUBTOTAL(9,OFFSET(N20,1,0):OFFSET(N24,-1,0)) -> 131441.59 | P24: {=IFERROR(OFFSET($E$6,ROW()-ROW(Annual_Periods),MATCH(P$6,Annual_Periods,0)) / OFFSET($E$11,0,MATCH(P$6,Annual_Periods,0)),"NA")} -> -60.901468 | Q24: {=IFERROR(OFFSET($E$6,ROW()-ROW(Annual_Periods),MATCH(Q$6,Annual_Periods,0)) / OFFSET($E$11,0,MATCH(Q$6,Annual_Periods,0)),"NA")} -> -19.484497 | R24: {=IFERROR(OFFSET($E$6,ROW()-ROW(Annual_Periods),MATCH(R$6,Annual_Periods,0)) / OFFSET($E$11,0,MATCH(R$6,Annual_Periods,0)),"NA")} -> -12.080886 | S24: {=IFERROR(OFFSET($E$6,ROW()-ROW(Annual_Periods),MATCH(S$6,Annual_Periods,0)) / OFFSET($E$11,0,MATCH(S$6,Annual_Periods,0)),"NA")} -> -3.7447699 | T24: {=IFERROR(OFFSET($E$6,ROW()-ROW(Annual_Periods),MATCH(T$6,Annual_Periods,0)) / OFFSET($E$11,0,MATCH(T$6,Annual_Periods,0)),"NA")} -> -2.65 | U24: {=IFERROR(OFFSET($E$6,ROW()-ROW(Annual_Periods),MATCH(U$6,Annual_Periods,0)) / OFFSET($E$11,0,MATCH(U$6,Annual_Periods,0)),"NA")} -> -1.5 | V24: {=IFERROR(OFFSET($E$6,ROW()-ROW(Annual_Periods),MATCH(V$6,Annual_Periods,0)) / OFFSET($E$11,0,MATCH(V$6,Annual_Periods,0)),"NA")} -> -0.4 | W24: {=IFERROR(OFFSET($E$6,ROW()-ROW(Annual_Periods),MATCH(W$6,Annual_Periods,0)) / OFFSET($E$11,0,MATCH(W$6,Annual_Periods,0)),"NA")} -> 0.16 | X24: {=IFERROR(OFFSET($E$6,ROW()-ROW(Annual_Periods),MATCH(X$6,Annual_Periods,0)) / OFFSET($E$11,0,MATCH(X$6,Annual_Periods,0)),"NA")} -> 0.2
D25: Depreciation | F25: 2018 | G25: 2521 | H25: 2380 | I25: 1665 | J25: =-J183 -> 1193.067 | K25: =-K183 -> 1581.9741 | L25: =-L183 -> 2601.0363 | M25: =-M183 -> 5106.7651 | N25: =-N183 -> 9489.607 | P25: {=IFERROR(ABS(OFFSET($E$6,ROW()-ROW(Annual_Periods),MATCH(P$6,Annual_Periods,0)) / OFFSET($E$11,0,MATCH(P$6,Annual_Periods,0))),"NA")} -> 0.70510133 | Q25: {=IFERROR(ABS(OFFSET($E$6,ROW()-ROW(Annual_Periods),MATCH(Q$6,Annual_Periods,0)) / OFFSET($E$11,0,MATCH(Q$6,Annual_Periods,0))),"NA")} -> 0.21357167 | R25: {=IFERROR(ABS(OFFSET($E$6,ROW()-ROW(Annual_Periods),MATCH(R$6,Annual_Periods,0)) / OFFSET($E$11,0,MATCH(R$6,Annual_Periods,0))),"NA")} -> 0.1043402 | S25: {=IFERROR(ABS(OFFSET($E$6,ROW()-ROW(Annual_Periods),MATCH(S$6,Annual_Periods,0)) / OFFSET($E$11,0,MATCH(S$6,Annual_Periods,0))),"NA")} -> 0.044945337 | T25: {=IFERROR(ABS(OFFSET($E$6,ROW()-ROW(Annual_Periods),MATCH(T$6,Annual_Periods,0)) / OFFSET($E$11,0,MATCH(T$6,Annual_Periods,0))),"NA")} -> 0.023004203 | U25: {=IFERROR(ABS(OFFSET($E$6,ROW()-ROW(Annual_Periods),MATCH(U$6,Annual_Periods,0)) / OFFSET($E$11,0,MATCH(U$6,Annual_Periods,0))),"NA")} -> 0.019064339 | V25: {=IFERROR(ABS(OFFSET($E$6,ROW()-ROW(Annual_Periods),MATCH(V$6,Annual_Periods,0)) / OFFSET($E$11,0,MATCH(V$6,Annual_Periods,0))),"NA")} -> 0.015672519 | W25: {=IFERROR(ABS(OFFSET($E$6,ROW()-ROW(Annual_Periods),MATCH(W$6,Annual_Periods,0)) / OFFSET($E$11,0,MATCH(W$6,Annual_Periods,0))),"NA")} -> 0.01398671 | X25: {=IFERROR(ABS(OFFSET($E$6,ROW()-ROW(Annual_Periods),MATCH(X$6,Annual_Periods,0)) / OFFSET($E$11,0,MATCH(X$6,Annual_Periods,0))),"NA")} -> 0.014439276
D26: Amortization | F26: 177 | G26: 177 | H26: 177 | I26: 177 | J26: =-J191 -> 237.98759 | K26: =-K191 -> 419.31895 | L26: =-L191 -> 1273.4235 | M26: =-M191 -> 2540.8552 | N26: =-N191 -> 4386.565 | P26: {=IFERROR(ABS(OFFSET($E$6,ROW()-ROW(Annual_Periods),MATCH(P$6,Annual_Periods,0)) / OFFSET($E$11,0,MATCH(P$6,Annual_Periods,0))),"NA")} -> 0.061844864 | Q26: {=IFERROR(ABS(OFFSET($E$6,ROW()-ROW(Annual_Periods),MATCH(Q$6,Annual_Periods,0)) / OFFSET($E$11,0,MATCH(Q$6,Annual_Periods,0))),"NA")} -> 0.014994917 | R26: {=IFERROR(ABS(OFFSET($E$6,ROW()-ROW(Annual_Periods),MATCH(R$6,Annual_Periods,0)) / OFFSET($E$11,0,MATCH(R$6,Annual_Periods,0))),"NA")} -> 0.0077597545 | S26: {=IFERROR(ABS(OFFSET($E$6,ROW()-ROW(Annual_Periods),MATCH(S$6,Annual_Periods,0)) / OFFSET($E$11,0,MATCH(S$6,Annual_Periods,0))),"NA")} -> 0.0047779727 | T26: {=IFERROR(ABS(OFFSET($E$6,ROW()-ROW(Annual_Periods),MATCH(T$6,Annual_Periods,0)) / OFFSET($E$11,0,MATCH(T$6,Annual_Periods,0))),"NA")} -> 0.004588774 | U26: {=IFERROR(ABS(OFFSET($E$6,ROW()-ROW(Annual_Periods),MATCH(U$6,Annual_Periods,0)) / OFFSET($E$11,0,MATCH(U$6,Annual_Periods,0))),"NA")} -> 0.0050532044 | V26: {=IFERROR(ABS(OFFSET($E$6,ROW()-ROW(Annual_Periods),MATCH(V$6,Annual_Periods,0)) / OFFSET($E$11,0,MATCH(V$6,Annual_Periods,0))),"NA")} -> 0.0076730007 | W26: {=IFERROR(ABS(OFFSET($E$6,ROW()-ROW(Annual_Periods),MATCH(W$6,Annual_Periods,0)) / OFFSET($E$11,0,MATCH(W$6,Annual_Periods,0))),"NA")} -> 0.0069590447 | X26: {=IFERROR(ABS(OFFSET($E$6,ROW()-ROW(Annual_Periods),MATCH(X$6,Annual_Periods,0)) / OFFSET($E$11,0,MATCH(X$6,Annual_Periods,0))),"NA")} -> 0.0066745466
D27: Total Operating Expenses | F27: =SUBTOTAL(9,F21:F23) -> 175392 | G27: =SUBTOTAL(9,G21:G23) -> 234482 | H27: =SUBTOTAL(9,H21:H23) -> 279414 | I27: =SUBTOTAL(9,I21:I23) -> 170833 | J27: =SUBTOTAL(9,J21:J23) -> 178927.35 | K27: =SUBTOTAL(9,K21:K23) -> 186706.8 | L27: =SUBTOTAL(9,L21:L23) -> 190855.84 | M27: =SUBTOTAL(9,M21:M23) -> 197162.38 | N27: =SUBTOTAL(9,N21:N23) -> 295743.57 | P27: {=IFERROR(ABS(OFFSET($E$6,ROW()-ROW(Annual_Periods),MATCH(P$6,Annual_Periods,0)) / OFFSET($E$11,0,MATCH(P$6,Annual_Periods,0))),"NA")} -> 61.283019 | Q27: {=IFERROR(ABS(OFFSET($E$6,ROW()-ROW(Annual_Periods),MATCH(Q$6,Annual_Periods,0)) / OFFSET($E$11,0,MATCH(Q$6,Annual_Periods,0))),"NA")} -> 19.864622 | R27: {=IFERROR(ABS(OFFSET($E$6,ROW()-ROW(Annual_Periods),MATCH(R$6,Annual_Periods,0)) / OFFSET($E$11,0,MATCH(R$6,Annual_Periods,0))),"NA")} -> 12.249627 | S27: {=IFERROR(ABS(OFFSET($E$6,ROW()-ROW(Annual_Periods),MATCH(S$6,Annual_Periods,0)) / OFFSET($E$11,0,MATCH(S$6,Annual_Periods,0))),"NA")} -> 4.6114995 | T27: {=IFERROR(ABS(OFFSET($E$6,ROW()-ROW(Annual_Periods),MATCH(T$6,Annual_Periods,0)) / OFFSET($E$11,0,MATCH(T$6,Annual_Periods,0))),"NA")} -> 3.45 | U27: {=IFERROR(ABS(OFFSET($E$6,ROW()-ROW(Annual_Periods),MATCH(U$6,Annual_Periods,0)) / OFFSET($E$11,0,MATCH(U$6,Annual_Periods,0))),"NA")} -> 2.25 | V27: {=IFERROR(ABS(OFFSET($E$6,ROW()-ROW(Annual_Periods),MATCH(V$6,Annual_Periods,0)) / OFFSET($E$11,0,MATCH(V$6,Annual_Periods,0))),"NA")} -> 1.15 | W27: {=IFERROR(ABS(OFFSET($E$6,ROW()-ROW(Annual_Periods),MATCH(W$6,Annual_Periods,0)) / OFFSET($E$11,0,MATCH(W$6,Annual_Periods,0))),"NA")} -> 0.54 | X27: {=IFERROR(ABS(OFFSET($E$6,ROW()-ROW(Annual_Periods),MATCH(X$6,Annual_Periods,0)) / OFFSET($E$11,0,MATCH(X$6,Annual_Periods,0))),"NA")} -> 0.45 | AE27: Avg Opex% of Sales | AF27: =AVERAGE(T27:X27) -> 1.568
D28: EBITDA | F28: =F24+F25+F26 -> -172105 | G28: =G24+G25+G26 -> -227297 | H28: =H24+H25+H26 -> -273008 | I28: =I24+I25+I26 -> -136883 | J28: =J24+J25+J26 -> -136005.9 | K28: =K24+K25+K26 -> -122469.91 | L28: =L24+L25+L26 -> -62510.18 | M28: =M24+M25+M26 -> 66066.103 | N28: =N24+N25+N26 -> 145317.76 | P28: {=IFERROR(OFFSET($E$6,ROW()-ROW(Annual_Periods),MATCH(P$6,Annual_Periods,0)) / OFFSET($E$11,0,MATCH(P$6,Annual_Periods,0)),"NA")} -> -60.134521 | Q28: {=IFERROR(OFFSET($E$6,ROW()-ROW(Annual_Periods),MATCH(Q$6,Annual_Periods,0)) / OFFSET($E$11,0,MATCH(Q$6,Annual_Periods,0)),"NA")} -> -19.25593 | R28: {=IFERROR(OFFSET($E$6,ROW()-ROW(Annual_Periods),MATCH(R$6,Annual_Periods,0)) / OFFSET($E$11,0,MATCH(R$6,Annual_Periods,0)),"NA")} -> -11.968786 | S28: {=IFERROR(OFFSET($E$6,ROW()-ROW(Annual_Periods),MATCH(S$6,Annual_Periods,0)) / OFFSET($E$11,0,MATCH(S$6,Annual_Periods,0)),"NA")} -> -3.6950466 | T28: {=IFERROR(OFFSET($E$6,ROW()-ROW(Annual_Periods),MATCH(T$6,Annual_Periods,0)) / OFFSET($E$11,0,MATCH(T$6,Annual_Periods,0)),"NA")} -> -2.622407 | U28: {=IFERROR(OFFSET($E$6,ROW()-ROW(Annual_Periods),MATCH(U$6,Annual_Periods,0)) / OFFSET($E$11,0,MATCH(U$6,Annual_Periods,0)),"NA")} -> -1.4758825 | V28: {=IFERROR(OFFSET($E$6,ROW()-ROW(Annual_Periods),MATCH(V$6,Annual_Periods,0)) / OFFSET($E$11,0,MATCH(V$6,Annual_Periods,0)),"NA")} -> -0.37665448 | W28: {=IFERROR(OFFSET($E$6,ROW()-ROW(Annual_Periods),MATCH(W$6,Annual_Periods,0)) / OFFSET($E$11,0,MATCH(W$6,Annual_Periods,0)),"NA")} -> 0.18094576 | X28: {=IFERROR(OFFSET($E$6,ROW()-ROW(Annual_Periods),MATCH(X$6,Annual_Periods,0)) / OFFSET($E$11,0,MATCH(X$6,Annual_Periods,0)),"NA")} -> 0.22111382
D29: EBITDA Margin % | F29: =IFERROR(F28/F$11,"NA") -> -60.134521 | G29: =IFERROR(G28/G$11,"NA") -> -19.25593 | H29: =IFERROR(H28/H$11,"NA") -> -11.968786 | I29: =IFERROR(I28/I$11,"NA") -> -3.6950466 | J29: =IFERROR(J28/J$11,"NA") -> -2.622407 | K29: =IFERROR(K28/K$11,"NA") -> -1.4758825 | L29: =IFERROR(L28/L$11,"NA") -> -0.37665448 | M29: =IFERROR(M28/M$11,"NA") -> 0.18094576 | N29: =IFERROR(N28/N$11,"NA") -> 0.22111382
D30: Total Operating (EBIT) Margin % | F30: =IFERROR(F24/F$11,"NA") -> -60.901468 | G30: =IFERROR(G24/G$11,"NA") -> -19.484497 | H30: =IFERROR(H24/H$11,"NA") -> -12.080886 | I30: =IFERROR(I24/I$11,"NA") -> -3.7447699 | J30: =IFERROR(J24/J$11,"NA") -> -2.65 | K30: =IFERROR(K24/K$11,"NA") -> -1.5 | L30: =IFERROR(L24/L$11,"NA") -> -0.4 | M30: =IFERROR(M24/M$11,"NA") -> 0.16 | N30: =IFERROR(N24/N$11,"NA") -> 0.2
D32: Other Income (Expense)
D33: Interest Income (Positive) | F33: - | G33: 3760 | H33: 10792 | I33: 0 | J33: =J$11*(Z33) -> 0 | K33: =K$11*(AA33) -> 0 | L33: =L$11*(AB33) -> 0 | M33: =M$11*(AC33) -> 0 | N33: =N$11*(AD33) -> 0 | P33: {=IFERROR(ABS(OFFSET($E$6,ROW()-ROW(Annual_Periods),MATCH(P$6,Annual_Periods,0)) / OFFSET($E$11,0,MATCH(P$6,Annual_Periods,0))),"NA")} -> NA | Q33: {=IFERROR(ABS(OFFSET($E$6,ROW()-ROW(Annual_Periods),MATCH(Q$6,Annual_Periods,0)) / OFFSET($E$11,0,MATCH(Q$6,Annual_Periods,0))),"NA")} -> 0.31853609 | R33: {=IFERROR(ABS(OFFSET($E$6,ROW()-ROW(Annual_Periods),MATCH(R$6,Annual_Periods,0)) / OFFSET($E$11,0,MATCH(R$6,Annual_Periods,0))),"NA")} -> 0.47312582 | S33: {=IFERROR(ABS(OFFSET($E$6,ROW()-ROW(Annual_Periods),MATCH(S$6,Annual_Periods,0)) / OFFSET($E$11,0,MATCH(S$6,Annual_Periods,0))),"NA")} -> 0 | T33: {=IFERROR(ABS(OFFSET($E$6,ROW()-ROW(Annual_Periods),MATCH(T$6,Annual_Periods,0)) / OFFSET($E$11,0,MATCH(T$6,Annual_Periods,0))),"NA")} -> 0 | U33: {=IFERROR(ABS(OFFSET($E$6,ROW()-ROW(Annual_Periods),MATCH(U$6,Annual_Periods,0)) / OFFSET($E$11,0,MATCH(U$6,Annual_Periods,0))),"NA")} -> 0 | V33: {=IFERROR(ABS(OFFSET($E$6,ROW()-ROW(Annual_Periods),MATCH(V$6,Annual_Periods,0)) / OFFSET($E$11,0,MATCH(V$6,Annual_Periods,0))),"NA")} -> 0 | W33: {=IFERROR(ABS(OFFSET($E$6,ROW()-ROW(Annual_Periods),MATCH(W$6,Annual_Periods,0)) / OFFSET($E$11,0,MATCH(W$6,Annual_Periods,0))),"NA")} -> 0 | X33: {=IFERROR(ABS(OFFSET($E$6,ROW()-ROW(Annual_Periods),MATCH(X$6,Annual_Periods,0)) / OFFSET($E$11,0,MATCH(X$6,Annual_Periods,0))),"NA")} -> 0
D34: Interest Expense (Negative) | F34: -1715 | G34: - | H34: - | I34: - | J34: =J$11*(Z34) -> 0 | K34: =K$11*(AA34) -> 0 | L34: =L$11*(AB34) -> 0 | M34: =M$11*(AC34) -> 0 | N34: =N$11*(AD34) -> 0 | P34: {=IFERROR(ABS(OFFSET($E$6,ROW()-ROW(Annual_Periods),MATCH(P$6,Annual_Periods,0)) / OFFSET($E$11,0,MATCH(P$6,Annual_Periods,0))),"NA")} -> 0.59923131 | Q34: {=IFERROR(ABS(OFFSET($E$6,ROW()-ROW(Annual_Periods),MATCH(Q$6,Annual_Periods,0)) / OFFSET($E$11,0,MATCH(Q$6,Annual_Periods,0))),"NA")} -> NA | R34: {=IFERROR(ABS(OFFSET($E$6,ROW()-ROW(Annual_Periods),MATCH(R$6,Annual_Periods,0)) / OFFSET($E$11,0,MATCH(R$6,Annual_Periods,0))),"NA")} -> NA | S34: {=IFERROR(ABS(OFFSET($E$6,ROW()-ROW(Annual_Periods),MATCH(S$6,Annual_Periods,0)) / OFFSET($E$11,0,MATCH(S$6,Annual_Periods,0))),"NA")} -> NA | T34: {=IFERROR(ABS(OFFSET($E$6,ROW()-ROW(Annual_Periods),MATCH(T$6,Annual_Periods,0)) / OFFSET($E$11,0,MATCH(T$6,Annual_Periods,0))),"NA")} -> 0 | U34: {=IFERROR(ABS(OFFSET($E$6,ROW()-ROW(Annual_Periods),MATCH(U$6,Annual_Periods,0)) / OFFSET($E$11,0,MATCH(U$6,Annual_Periods,0))),"NA")} -> 0 | V34: {=IFERROR(ABS(OFFSET($E$6,ROW()-ROW(Annual_Periods),MATCH(V$6,Annual_Periods,0)) / OFFSET($E$11,0,MATCH(V$6,Annual_Periods,0))),"NA")} -> 0 | W34: {=IFERROR(ABS(OFFSET($E$6,ROW()-ROW(Annual_Periods),MATCH(W$6,Annual_Periods,0)) / OFFSET($E$11,0,MATCH(W$6,Annual_Periods,0))),"NA")} -> 0 | X34: {=IFERROR(ABS(OFFSET($E$6,ROW()-ROW(Annual_Periods),MATCH(X$6,Annual_Periods,0)) / OFFSET($E$11,0,MATCH(X$6,Annual_Periods,0))),"NA")} -> 0
D35: Total Other Income (Expense) | F35: =SUBTOTAL(9,OFFSET(F32,1,0):OFFSET(F35,-1,0)) -> -1715 | G35: =SUBTOTAL(9,OFFSET(G32,1,0):OFFSET(G35,-1,0)) -> 3760 | H35: =SUBTOTAL(9,OFFSET(H32,1,0):OFFSET(H35,-1,0)) -> 10792 | I35: =SUBTOTAL(9,OFFSET(I32,1,0):OFFSET(I35,-1,0)) -> 0 | J35: =SUBTOTAL(9,OFFSET(J32,1,0):OFFSET(J35,-1,0)) -> 0 | K35: =SUBTOTAL(9,OFFSET(K32,1,0):OFFSET(K35,-1,0)) -> 0 | L35: =SUBTOTAL(9,OFFSET(L32,1,0):OFFSET(L35,-1,0)) -> 0 | M35: =SUBTOTAL(9,OFFSET(M32,1,0):OFFSET(M35,-1,0)) -> 0 | N35: =SUBTOTAL(9,OFFSET(N32,1,0):OFFSET(N35,-1,0)) -> 0 | P35: {=IFERROR(ABS(OFFSET($E$6,ROW()-ROW(Annual_Periods),MATCH(P$6,Annual_Periods,0)) / OFFSET($E$11,0,MATCH(P$6,Annual_Periods,0))),"NA")} -> 0.59923131 | Q35: {=IFERROR(ABS(OFFSET($E$6,ROW()-ROW(Annual_Periods),MATCH(Q$6,Annual_Periods,0)) / OFFSET($E$11,0,MATCH(Q$6,Annual_Periods,0))),"NA")} -> 0.31853609 | R35: {=IFERROR(ABS(OFFSET($E$6,ROW()-ROW(Annual_Periods),MATCH(R$6,Annual_Periods,0)) / OFFSET($E$11,0,MATCH(R$6,Annual_Periods,0))),"NA")} -> 0.47312582 | S35: {=IFERROR(ABS(OFFSET($E$6,ROW()-ROW(Annual_Periods),MATCH(S$6,Annual_Periods,0)) / OFFSET($E$11,0,MATCH(S$6,Annual_Periods,0))),"NA")} -> 0 | T35: {=IFERROR(ABS(OFFSET($E$6,ROW()-ROW(Annual_Periods),MATCH(T$6,Annual_Periods,0)) / OFFSET($E$11,0,MATCH(T$6,Annual_Periods,0))),"NA")} -> 0 | U35: {=IFERROR(ABS(OFFSET($E$6,ROW()-ROW(Annual_Periods),MATCH(U$6,Annual_Periods,0)) / OFFSET($E$11,0,MATCH(U$6,Annual_Periods,0))),"NA")} -> 0 | V35: {=IFERROR(ABS(OFFSET($E$6,ROW()-ROW(Annual_Periods),MATCH(V$6,Annual_Periods,0)) / OFFSET($E$11,0,MATCH(V$6,Annual_Periods,0))),"NA")} -> 0 | W35: {=IFERROR(ABS(OFFSET($E$6,ROW()-ROW(Annual_Periods),MATCH(W$6,Annual_Periods,0)) / OFFSET($E$11,0,MATCH(W$6,Annual_Periods,0))),"NA")} -> 0 | X35: {=IFERROR(ABS(OFFSET($E$6,ROW()-ROW(Annual_Periods),MATCH(X$6,Annual_Periods,0)) / OFFSET($E$11,0,MATCH(X$6,Annual_Periods,0))),"NA")} -> 0
D36: EBT | F36: =F24+F35 -> -176015 | G36: =G24+G35 -> -226235 | H36: =H24+H35 -> -264773 | I36: =I24+I35 -> -138725 | J36: =J24+J35 -> -137436.95 | K36: =K24+K35 -> -124471.2 | L36: =L24+L35 -> -66384.64 | M36: =M24+M35 -> 58418.483 | N36: =N24+N35 -> 131441.59 | P36: {=IFERROR(OFFSET($E$6,ROW()-ROW(Annual_Periods),MATCH(P$6,Annual_Periods,0)) / OFFSET($E$11,0,MATCH(P$6,Annual_Periods,0)),"NA")} -> -61.500699 | Q36: {=IFERROR(OFFSET($E$6,ROW()-ROW(Annual_Periods),MATCH(Q$6,Annual_Periods,0)) / OFFSET($E$11,0,MATCH(Q$6,Annual_Periods,0)),"NA")} -> -19.165961 | R36: {=IFERROR(OFFSET($E$6,ROW()-ROW(Annual_Periods),MATCH(R$6,Annual_Periods,0)) / OFFSET($E$11,0,MATCH(R$6,Annual_Periods,0)),"NA")} -> -11.60776 | S36: {=IFERROR(OFFSET($E$6,ROW()-ROW(Annual_Periods),MATCH(S$6,Annual_Periods,0)) / OFFSET($E$11,0,MATCH(S$6,Annual_Periods,0)),"NA")} -> -3.7447699 | T36: {=IFERROR(OFFSET($E$6,ROW()-ROW(Annual_Periods),MATCH(T$6,Annual_Periods,0)) / OFFSET($E$11,0,MATCH(T$6,Annual_Periods,0)),"NA")} -> -2.65 | U36: {=IFERROR(OFFSET($E$6,ROW()-ROW(Annual_Periods),MATCH(U$6,Annual_Periods,0)) / OFFSET($E$11,0,MATCH(U$6,Annual_Periods,0)),"NA")} -> -1.5 | V36: {=IFERROR(OFFSET($E$6,ROW()-ROW(Annual_Periods),MATCH(V$6,Annual_Periods,0)) / OFFSET($E$11,0,MATCH(V$6,Annual_Periods,0)),"NA")} -> -0.4 | W36: {=IFERROR(OFFSET($E$6,ROW()-ROW(Annual_Periods),MATCH(W$6,Annual_Periods,0)) / OFFSET($E$11,0,MATCH(W$6,Annual_Periods,0)),"NA")} -> 0.16 | X36: {=IFERROR(OFFSET($E$6,ROW()-ROW(Annual_Periods),MATCH(X$6,Annual_Periods,0)) / OFFSET($E$11,0,MATCH(X$6,Annual_Periods,0)),"NA")} -> 0.2
D38: Taxation
D39: Taxes (Enter as Negative for Taxes Paid) | J39: =-J$36*(Z39) -> 0 | K39: =-K$36*(AA39) -> 0 | L39: =-L$36*(AB39) -> 0 | M39: =-M$36*(AC39) -> 0 | N39: =-N$36*(AD39) -> 0 | P39: =-F39/F36 -> 0 | Q39: =-G39/G36 -> 0 | R39: =-H39/H36 -> 0 | S39: =-I39/I36 -> 0 | T39: =-J39/J36 -> 0 | U39: =-K39/K36 -> 0 | V39: =-L39/L36 -> 0 | W39: =-M39/M36 -> 0 | X39: =-N39/N36 -> 0
D40: Net Income from Continuing Operations | F40: =F36+F39 -> -176015 | G40: =G36+G39 -> -226235 | H40: =H36+H39 -> -264773 | I40: =I36+I39 -> -138725 | J40: =J36+J39 -> -137436.95 | K40: =K36+K39 -> -124471.2 | L40: =L36+L39 -> -66384.64 | M40: =M36+M39 -> 58418.483 | N40: =N36+N39 -> 131441.59 | P40: {=IFERROR(OFFSET($E$6,ROW()-ROW(Annual_Periods),MATCH(P$6,Annual_Periods,0)) / OFFSET($E$11,0,MATCH(P$6,Annual_Periods,0)),"NA")} -> -61.500699 | Q40: {=IFERROR(OFFSET($E$6,ROW()-ROW(Annual_Periods),MATCH(Q$6,Annual_Periods,0)) / OFFSET($E$11,0,MATCH(Q$6,Annual_Periods,0)),"NA")} -> -19.165961 | R40: {=IFERROR(OFFSET($E$6,ROW()-ROW(Annual_Periods),MATCH(R$6,Annual_Periods,0)) / OFFSET($E$11,0,MATCH(R$6,Annual_Periods,0)),"NA")} -> -11.60776 | S40: {=IFERROR(OFFSET($E$6,ROW()-ROW(Annual_Periods),MATCH(S$6,Annual_Periods,0)) / OFFSET($E$11,0,MATCH(S$6,Annual_Periods,0)),"NA")} -> -3.7447699 | T40: {=IFERROR(OFFSET($E$6,ROW()-ROW(Annual_Periods),MATCH(T$6,Annual_Periods,0)) / OFFSET($E$11,0,MATCH(T$6,Annual_Periods,0)),"NA")} -> -2.65 | U40: {=IFERROR(OFFSET($E$6,ROW()-ROW(Annual_Periods),MATCH(U$6,Annual_Periods,0)) / OFFSET($E$11,0,MATCH(U$6,Annual_Periods,0)),"NA")} -> -1.5 | V40: {=IFERROR(OFFSET($E$6,ROW()-ROW(Annual_Periods),MATCH(V$6,Annual_Periods,0)) / OFFSET($E$11,0,MATCH(V$6,Annual_Periods,0)),"NA")} -> -0.4 | W40: {=IFERROR(OFFSET($E$6,ROW()-ROW(Annual_Periods),MATCH(W$6,Annual_Periods,0)) / OFFSET($E$11,0,MATCH(W$6,Annual_Periods,0)),"NA")} -> 0.16 | X40: {=IFERROR(OFFSET($E$6,ROW()-ROW(Annual_Periods),MATCH(X$6,Annual_Periods,0)) / OFFSET($E$11,0,MATCH(X$6,Annual_Periods,0)),"NA")} -> 0.2
D41: Profit Margin % | F41: =IFERROR(F40/F$11,"NA") -> -61.500699 | G41: =IFERROR(G40/G$11,"NA") -> -19.165961 | H41: =IFERROR(H40/H$11,"NA") -> -11.60776 | I41: =IFERROR(I40/I$11,"NA") -> -3.7447699 | J41: =IFERROR(J40/J$11,"NA") -> -2.65 | K41: =IFERROR(K40/K$11,"NA") -> -1.5 | L41: =IFERROR(L40/L$11,"NA") -> -0.4 | M41: =IFERROR(M40/M$11,"NA") -> 0.16 | N41: =IFERROR(N40/N$11,"NA") -> 0.2
D43: Retained Earnings
D44: Beginning of Period | G44: =OFFSET(G47,0,-1) -> - | H44: =OFFSET(H47,0,-1) -> 296748 | I44: =OFFSET(I47,0,-1) -> 333888 | J44: =OFFSET(J47,0,-1) -> 995745 | K44: =OFFSET(K47,0,-1) -> 858308.05 | L44: =OFFSET(L47,0,-1) -> 733836.85 | M44: =OFFSET(M47,0,-1) -> 667452.21 | N44: =OFFSET(N47,0,-1) -> 725870.69
D45: Net Income | F45: =F$40 -> -176015 | G45: =G$40 -> -226235 | H45: =H$40 -> -264773 | I45: =I$40 -> -138725 | J45: =J$40 -> -137436.95 | K45: =K$40 -> -124471.2 | L45: =L$40 -> -66384.64 | M45: =M$40 -> 58418.483 | N45: =N$40 -> 131441.59
D46: PLUG (Dividends, Other Adj, Etc.) | F46: =F47-F45-F44 -> #VALUE! | G46: =G47-G45-G44 -> #VALUE! | H46: =H47-H45-H44 -> 301913 | I46: =I47-I45-I44 -> 800582 | J46: 0 | K46: 0 | L46: 0 | M46: 0 | N46: 0
D47: End of Period | F47: =F$94 -> - | G47: =G$94 -> 296748 | H47: =H$94 -> 333888 | I47: =I$94 -> 995745 | J47: =SUBTOTAL(9,OFFSET(J43,1,0):OFFSET(J47,-1,0)) -> 858308.05 | K47: =SUBTOTAL(9,OFFSET(K43,1,0):OFFSET(K47,-1,0)) -> 733836.85 | L47: =SUBTOTAL(9,OFFSET(L43,1,0):OFFSET(L47,-1,0)) -> 667452.21 | M47: =SUBTOTAL(9,OFFSET(M43,1,0):OFFSET(M47,-1,0)) -> 725870.69 | N47: =SUBTOTAL(9,OFFSET(N43,1,0):OFFSET(N47,-1,0)) -> 857312.28
A49: X | B49: Balance Sheet Toggles | D49: Balance Sheet
D50: Assets
D51: Current Assets
B52: CASH | D52: Cash | F52: 77094 | G52: 217685 | H52: 120265 | I52: 401556 | J52: =J126 -> 210462.67 | K52: =K126 -> 120513.86 | L52: =L126 -> 70552.733 | M52: =M126 -> 228742.56 | N52: =N126 -> 629682.63
B53: CASH | D53: Marketable Securities | F53: 0 | G53: 0 | H53: 0 | I53: 40000 | J53: =I53 -> 40000 | K53: =J53 -> 40000 | L53: =K53 -> 40000 | M53: =L53 -> 40000 | N53: =M53 -> 40000
B54: STA | D54: Accounts Receivable (Net of Doubtful) | F54: 4833 | G54: 11199 | H54: 10127 | I54: 21104 | J54: =J140 -> 21313.562 | K54: =K140 -> 34101.699 | L54: =L140 -> 65929.951 | M54: =M140 -> 145045.89 | N54: =N140 -> 261082.6
B55: STA | D55: Inventory | F55: 0 | G55: 0 | H55: 0 | I55: 0 | J55: =J146 -> 0 | K55: =K146 -> 0 | L55: =L146 -> 0 | M55: =M146 -> 0 | N55: =N146 -> 0
B56: STA | D56: Unbilled Revenue | F56: 0 | G56: 0 | H56: 5100 | I56: 5100 | J56: =J152 -> 6223.56 | K56: =K152 -> 8298.08 | L56: =L152 -> 13276.928 | M56: =M152 -> 29209.242 | N56: =N152 -> 32860.397
B57: STA | D57: Other Current Assets | F57: 4147 | G57: 5531 | H57: 19054 | I57: 3377 | J57: =J157 -> 17368.2 | K57: =K157 -> 12447.12 | L57: =L157 -> 33192.32 | M57: =M157 -> 79661.568 | N57: =N157 -> 116836.97
D58: Total Current Assets | F58: =SUBTOTAL(9,OFFSET(F51,1,0):OFFSET(F58,-1,0)) -> 86074 | G58: =SUBTOTAL(9,OFFSET(G51,1,0):OFFSET(G58,-1,0)) -> 234415 | H58: =SUBTOTAL(9,OFFSET(H51,1,0):OFFSET(H58,-1,0)) -> 154546 | I58: =SUBTOTAL(9,OFFSET(I51,1,0):OFFSET(I58,-1,0)) -> 471137 | J58: =SUBTOTAL(9,OFFSET(J51,1,0):OFFSET(J58,-1,0)) -> 295367.99 | K58: =SUBTOTAL(9,OFFSET(K51,1,0):OFFSET(K58,-1,0)) -> 215360.76 | L58: =SUBTOTAL(9,OFFSET(L51,1,0):OFFSET(L58,-1,0)) -> 222951.93 | M58: =SUBTOTAL(9,OFFSET(M51,1,0):OFFSET(M58,-1,0)) -> 522659.27 | N58: =SUBTOTAL(9,OFFSET(N51,1,0):OFFSET(N58,-1,0)) -> 1080462.6
D60: Long-Term Assets
B61: LTA | D61: Net PP&E | F61: 4960 | G61: 4770 | H61: 4116 | I61: 2421 | J61: =J184 -> 2783.823 | K61: =K184 -> 3691.2729 | L61: =L184 -> 6069.0846 | M61: =M184 -> 11915.785 | N61: =N184 -> 22142.416
D62: Goodwill & Intangibles | F62: 26391 | G62: 26214 | H62: 26037 | I62: 25859 | J62: =I62 -> 25859 | K62: =J62 -> 25859 | L62: =K62 -> 25859 | M62: =L62 -> 25859 | N62: =M62 -> 25859
B63: LTA | D63: Deferred Tax Assets | J63: =J192 -> 237.98759 | K63: =K192 -> 419.31895 | L63: =L192 -> 318.35587 | M63: =M192 -> 635.2138 | N63: =N192 -> 1096.6412
B64: NOA | D64: Other Non-Current Assets | F64: 3772 | G64: 33236 | H64: 40159 | I64: 45256 | J64: =I64 -> 45256 | K64: =J64 -> 45256 | L64: =K64 -> 45256 | M64: =L64 -> 45256 | N64: =M64 -> 45256
B65: LTA | J65: =I65 -> 0 | K65: =J65 -> 0 | L65: =K65 -> 0 | M65: =L65 -> 0 | N65: =M65 -> 0
D66: Total Long-Term Assets | F66: =SUBTOTAL(9,OFFSET(F60,1,0):OFFSET(F66,-1,0)) -> 35123 | G66: =SUBTOTAL(9,OFFSET(G60,1,0):OFFSET(G66,-1,0)) -> 64220 | H66: =SUBTOTAL(9,OFFSET(H60,1,0):OFFSET(H66,-1,0)) -> 70312 | I66: =SUBTOTAL(9,OFFSET(I60,1,0):OFFSET(I66,-1,0)) -> 73536 | J66: =SUBTOTAL(9,OFFSET(J60,1,0):OFFSET(J66,-1,0)) -> 74136.811 | K66: =SUBTOTAL(9,OFFSET(K60,1,0):OFFSET(K66,-1,0)) -> 75225.592 | L66: =SUBTOTAL(9,OFFSET(L60,1,0):OFFSET(L66,-1,0)) -> 77502.44 | M66: =SUBTOTAL(9,OFFSET(M60,1,0):OFFSET(M66,-1,0)) -> 83665.999 | N66: =SUBTOTAL(9,OFFSET(N60,1,0):OFFSET(N66,-1,0)) -> 94354.058
D68: Total Assets | F68: =SUBTOTAL(9,OFFSET(F50,1,0):OFFSET(F68,-1,0)) -> 121197 | G68: =SUBTOTAL(9,OFFSET(G50,1,0):OFFSET(G68,-1,0)) -> 298635 | H68: =SUBTOTAL(9,OFFSET(H50,1,0):OFFSET(H68,-1,0)) -> 224858 | I68: =SUBTOTAL(9,OFFSET(I50,1,0):OFFSET(I68,-1,0)) -> 544673 | J68: =SUBTOTAL(9,OFFSET(J50,1,0):OFFSET(J68,-1,0)) -> 369504.8 | K68: =SUBTOTAL(9,OFFSET(K50,1,0):OFFSET(K68,-1,0)) -> 290586.35 | L68: =SUBTOTAL(9,OFFSET(L50,1,0):OFFSET(L68,-1,0)) -> 300454.37 | M68: =SUBTOTAL(9,OFFSET(M50,1,0):OFFSET(M68,-1,0)) -> 606325.26 | N68: =SUBTOTAL(9,OFFSET(N50,1,0):OFFSET(N68,-1,0)) -> 1174816.7
D70: Liabilities
D71: Current Liabilities
B72: STL | D72: Accounts Payable | F72: 22375 | G72: 27951 | H72: 44925 | I72: 47947 | J72: =J164 -> 28418.082 | K72: =K164 -> 56836.164 | L72: =L164 -> 113672.33 | M72: =M164 -> 300094.95 | N72: =N164 -> 630199.39
B73: STL | D73: Accrued Expenses | F73: 10552 | G73: 9038 | H73: 8546 | I73: 7330 | J73: =J170 -> 8525.4247 | K73: =K170 -> 17050.849 | L73: =L170 -> 34101.699 | M73: =M170 -> 90028.484 | N73: =N170 -> 189059.82
B74: STL | D74: Deferred/ Unearned Revenue | I74: 762 | J74: =I74*1.1 -> 838.2 | K74: =J74*1.1 -> 922.02 | L74: =K74*1.1 -> 1014.222 | M74: =L74*1.1 -> 1115.6442 | N74: =M74*1.1 -> 1227.2086
B75: FC | D75: Current Debt | J75: =J205 -> 0 | K75: =K205 -> 0 | L75: =L205 -> 0 | M75: =M205 -> 0 | N75: =N205 -> 0
B76: STL | D76: Current Income Tax Payable | J76: =I76 -> 0 | K76: =J76 -> 0 | L76: =K76 -> 0 | M76: =L76 -> 0 | N76: =M76 -> 0
B77: STL | D77: Other Current Liabilities | F77: 15481 | G77: 1568 | H77: 33987 | I77: 33683 | J77: =J176 -> 14209.041 | K77: =K176 -> 22734.466 | L77: =L176 -> 25007.912 | M77: =M176 -> 30009.495 | N77: =N176 -> 37811.963
D78: Total Current Liabilities | F78: =SUBTOTAL(9,OFFSET(F71,1,0):OFFSET(F78,-1,0)) -> 48408 | G78: =SUBTOTAL(9,OFFSET(G71,1,0):OFFSET(G78,-1,0)) -> 38557 | H78: =SUBTOTAL(9,OFFSET(H71,1,0):OFFSET(H78,-1,0)) -> 87458 | I78: =SUBTOTAL(9,OFFSET(I71,1,0):OFFSET(I78,-1,0)) -> 89722 | J78: =SUBTOTAL(9,OFFSET(J71,1,0):OFFSET(J78,-1,0)) -> 51990.748 | K78: =SUBTOTAL(9,OFFSET(K71,1,0):OFFSET(K78,-1,0)) -> 97543.499 | L78: =SUBTOTAL(9,OFFSET(L71,1,0):OFFSET(L78,-1,0)) -> 173796.16 | M78: =SUBTOTAL(9,OFFSET(M71,1,0):OFFSET(M78,-1,0)) -> 421248.57 | N78: =SUBTOTAL(9,OFFSET(N71,1,0):OFFSET(N78,-1,0)) -> 858298.38
D80: Long-Term Liabilities
B81: FC | D81: Long-Term Debt | J81: =J210 -> 0 | K81: =K210 -> 0 | L81: =L210 -> 0 | M81: =M210 -> 0 | N81: =N210 -> 0
B82: FC | D82: Long-Term Leases | J82: =I82 -> 0 | K82: =J82 -> 0 | L82: =K82 -> 0 | M82: =L82 -> 0 | N82: =M82 -> 0
B83: NOL | D83: Deferred Expenses (Long Term) | F83: 1415 | G83: 856 | H83: 898 | I83: 181 | J83: =I83 -> 181 | K83: =J83 -> 181 | L83: =K83 -> 181 | M83: =L83 -> 181 | N83: =M83 -> 181
B84: NOL | D84: Other Non-Current Liabilities | F84: 2976 | G84: 32135 | H84: 7164 | I84: 1650 | J84: =I84 -> 1650 | K84: =J84 -> 1650 | L84: =K84 -> 1650 | M84: =L84 -> 1650 | N84: =M84 -> 1650
D85: Total Long-Term Liabilities | F85: =SUBTOTAL(9,OFFSET(F80,1,0):OFFSET(F85,-1,0)) -> 4391 | G85: =SUBTOTAL(9,OFFSET(G80,1,0):OFFSET(G85,-1,0)) -> 32991 | H85: =SUBTOTAL(9,OFFSET(H80,1,0):OFFSET(H85,-1,0)) -> 8062 | I85: =SUBTOTAL(9,OFFSET(I80,1,0):OFFSET(I85,-1,0)) -> 1831 | J85: =SUBTOTAL(9,OFFSET(J80,1,0):OFFSET(J85,-1,0)) -> 1831 | K85: =SUBTOTAL(9,OFFSET(K80,1,0):OFFSET(K85,-1,0)) -> 1831 | L85: =SUBTOTAL(9,OFFSET(L80,1,0):OFFSET(L85,-1,0)) -> 1831 | M85: =SUBTOTAL(9,OFFSET(M80,1,0):OFFSET(M85,-1,0)) -> 1831 | N85: =SUBTOTAL(9,OFFSET(N80,1,0):OFFSET(N85,-1,0)) -> 1831
D87: Total Liabilities | F87: =SUBTOTAL(9,OFFSET(F70,1,0):OFFSET(F87,-1,0)) -> 52799 | G87: =SUBTOTAL(9,OFFSET(G70,1,0):OFFSET(G87,-1,0)) -> 71548 | H87: =SUBTOTAL(9,OFFSET(H70,1,0):OFFSET(H87,-1,0)) -> 95520 | I87: =SUBTOTAL(9,OFFSET(I70,1,0):OFFSET(I87,-1,0)) -> 91553 | J87: =SUBTOTAL(9,OFFSET(J70,1,0):OFFSET(J87,-1,0)) -> 53821.748 | K87: =SUBTOTAL(9,OFFSET(K70,1,0):OFFSET(K87,-1,0)) -> 99374.499 | L87: =SUBTOTAL(9,OFFSET(L70,1,0):OFFSET(L87,-1,0)) -> 175627.16 | M87: =SUBTOTAL(9,OFFSET(M70,1,0):OFFSET(M87,-1,0)) -> 423079.57 | N87: =SUBTOTAL(9,OFFSET(N70,1,0):OFFSET(N87,-1,0)) -> 860129.38
D89: Equity
D90: Capital/Common Stock | F90: 28184 | G90: 23 | H90: 23 | I90: 27 | J90: =I90 -> 27 | K90: =J90 -> 27 | L90: =K90 -> 27 | M90: =L90 -> 27 | N90: =M90 -> 27
D91: Preferred Stock | F91: 819694 | G91: -- | H91: -- | I91: -- | J91: -- | K91: -- | L91: -- | M91: -- | N91: --
D92: Retained Earnings | F92: -781620 | G92: -182092 | H92: -240454 | I92: -377077 | J92: =J47 -> 858308.05 | K92: =K47 -> 733836.85 | L92: =L47 -> 667452.21 | M92: =M47 -> 725870.69 | N92: =N47 -> 857312.28
D93: Non Controlling Int | F93: - | G93: =162408-50000 -> 112408 | H93: 35881 | I93: -165575 | J93: =AVERAGE(G92:I92) -> -266541 | K93: =AVERAGE(J93,H92:I92) -> -294690.67 | L93: =AVERAGE(J93:K93,I92) -> -312769.56 | M93: =AVERAGE(J93:L93) -> -291333.74 | N93: =AVERAGE(K93:M93) -> -299597.99
D94: Additional Paid In Capital | F94: - | G94: 296748 | H94: 333888 | I94: 995745 | J94: 0 | K94: 0 | L94: 0 | M94: 0 | N94: 0
D95: Other Equity | F95: 2140 | G95: - | H95: - | J95: =I95 -> 0 | K95: =J95 -> 0 | L95: =K95 -> 0 | M95: =L95 -> 0 | N95: =M95 -> 0
D96: Total Equity | F96: =SUBTOTAL(9,OFFSET(F89,1,0):OFFSET(F96,-1,0)) -> 68398 | G96: =SUBTOTAL(9,OFFSET(G89,1,0):OFFSET(G96,-1,0)) -> 227087 | H96: =SUBTOTAL(9,OFFSET(H89,1,0):OFFSET(H96,-1,0)) -> 129338 | I96: =SUBTOTAL(9,OFFSET(I89,1,0):OFFSET(I96,-1,0)) -> 453120 | J96: =SUBTOTAL(9,OFFSET(J89,1,0):OFFSET(J96,-1,0)) -> 591794.05 | K96: =SUBTOTAL(9,OFFSET(K89,1,0):OFFSET(K96,-1,0)) -> 439173.18 | L96: =SUBTOTAL(9,OFFSET(L89,1,0):OFFSET(L96,-1,0)) -> 354709.65 | M96: =SUBTOTAL(9,OFFSET(M89,1,0):OFFSET(M96,-1,0)) -> 434563.95 | N96: =SUBTOTAL(9,OFFSET(N89,1,0):OFFSET(N96,-1,0)) -> 557741.29
D98: Total Liabilities & Equity | F98: =F87+F96 -> 121197 | G98: =G87+G96 -> 298635 | H98: =H87+H96 -> 224858 | I98: =I87+I96 -> 544673 | J98: =J87+J96 -> 645615.8 | K98: =K87+K96 -> 538547.68 | L98: =L87+L96 -> 530336.82 | M98: =M87+M96 -> 857643.52 | N98: =N87+N96 -> 1417870.7
D100: Balance Check | F100: =ROUND(F68-F98,0) -> 0 | G100: =ROUND(G68-G98,0) -> 0 | H100: =ROUND(H68-H98,0) -> 0 | I100: =ROUND(I68-I98,0) -> 0 | J100: =ROUND(J68-J98,0) -> -276111 | K100: =ROUND(K68-K98,0) -> -247961 | L100: =ROUND(L68-L98,0) -> -229882 | M100: =ROUND(M68-M98,0) -> -251318 | N100: =ROUND(N68-N98,0) -> -243054
D102: Addendum Items
D103: Net Working Capital | F103: =SUMIF($B$49:$B$102,"STA",F$49:F$102)-SUMIF($B$49:$B$102,"STL",F$49:F$102) -> -39428 | G103: =SUMIF($B$49:$B$102,"STA",G$49:G$102)-SUMIF($B$49:$B$102,"STL",G$49:G$102) -> -21827 | H103: =SUMIF($B$49:$B$102,"STA",H$49:H$102)-SUMIF($B$49:$B$102,"STL",H$49:H$102) -> -53177 | I103: =SUMIF($B$49:$B$102,"STA",I$49:I$102)-SUMIF($B$49:$B$102,"STL",I$49:I$102) -> -60141 | J103: =SUMIF($B$49:$B$102,"STA",J$49:J$102)-SUMIF($B$49:$B$102,"STL",J$49:J$102) -> -7085.4263 | K103: =SUMIF($B$49:$B$102,"STA",K$49:K$102)-SUMIF($B$49:$B$102,"STL",K$49:K$102) -> -42696.601 | L103: =SUMIF($B$49:$B$102,"STA",L$49:L$102)-SUMIF($B$49:$B$102,"STL",L$49:L$102) -> -61396.963 | M103: =SUMIF($B$49:$B$102,"STA",M$49:M$102)-SUMIF($B$49:$B$102,"STL",M$49:M$102) -> -167331.87 | N103: =SUMIF($B$49:$B$102,"STA",N$49:N$102)-SUMIF($B$49:$B$102,"STL",N$49:N$102) -> -447518.41
D104: ∆ Net Working Capital | F104: =F103-OFFSET(F103,0,-1) -> -39428 | G104: =G103-OFFSET(G103,0,-1) -> 17601 | H104: =H103-OFFSET(H103,0,-1) -> -31350 | I104: =I103-OFFSET(I103,0,-1) -> -6964 | J104: =J103-OFFSET(J103,0,-1) -> 53055.574 | K104: =K103-OFFSET(K103,0,-1) -> -35611.175 | L104: =L103-OFFSET(L103,0,-1) -> -18700.362 | M104: =M103-OFFSET(M103,0,-1) -> -105934.91 | N104: =N103-OFFSET(N103,0,-1) -> -280186.54
A106: X | D106: Statement of Cash Flows
D107: Cash Flow from Operations
D108: Net Income | J108: =J$40 -> -137436.95 | K108: =K$40 -> -124471.2 | L108: =L$40 -> -66384.64 | M108: =M$40 -> 58418.483 | N108: =N$40 -> 131441.59
D109: ∆ Net Working Capital | J109: =-J$104 -> -53055.574 | K109: =-K$104 -> 35611.175 | L109: =-L$104 -> 18700.362 | M109: =-M$104 -> 105934.91 | N109: =-N$104 -> 280186.54
D110: Depreciation & Amortization | J110: =-(J183+J191) -> 1431.0546 | K110: =-(K183+K191) -> 2001.293 | L110: =-(L183+L191) -> 3874.4597 | M110: =-(M183+M191) -> 7647.6203 | N110: =-(N183+N191) -> 13876.172
D111: Net Cash Flow from Operating Activities | J111: =SUBTOTAL(9,OFFSET(J107,1,0):OFFSET(J111,-1,0)) -> -189061.47 | K111: =SUBTOTAL(9,OFFSET(K107,1,0):OFFSET(K111,-1,0)) -> -86858.732 | L111: =SUBTOTAL(9,OFFSET(L107,1,0):OFFSET(L111,-1,0)) -> -43809.818 | M111: =SUBTOTAL(9,OFFSET(M107,1,0):OFFSET(M111,-1,0)) -> 172001.01 | N111: =SUBTOTAL(9,OFFSET(N107,1,0):OFFSET(N111,-1,0)) -> 425504.3
D113: Cash Flow from Investing Activities
D114: Capex | J114: =-(J$182+J$190) -> -2031.8652 | K114: =-(K$182+K$190) -> -3090.0743 | L114: =-(L$182+L$190) -> -6151.3084 | M114: =-(M$182+M$190) -> -13811.179 | N114: =-(N$182+N$190) -> -24564.23
D115: Net Cash Flow from Investing Activities | J115: =SUBTOTAL(9,OFFSET(J113,1,0):OFFSET(J115,-1,0)) -> -2031.8652 | K115: =SUBTOTAL(9,OFFSET(K113,1,0):OFFSET(K115,-1,0)) -> -3090.0743 | L115: =SUBTOTAL(9,OFFSET(L113,1,0):OFFSET(L115,-1,0)) -> -6151.3084 | M115: =SUBTOTAL(9,OFFSET(M113,1,0):OFFSET(M115,-1,0)) -> -13811.179 | N115: =SUBTOTAL(9,OFFSET(N113,1,0):OFFSET(N115,-1,0)) -> -24564.23
D117: Cash Flow from Financing Activities
D118: Dividends / Ownership Distributions | J118: =J46 -> 0 | K118: =K46 -> 0 | L118: =L46 -> 0 | M118: =M46 -> 0 | N118: =N46 -> 0
D119: Note Issuance (Payments) | J119: =J199 -> 0 | K119: =K199 -> 0 | L119: =L199 -> 0 | M119: =M199 -> 0 | N119: =N199 -> 0
D120: Current Debt Issuance (Payments) | J120: =J204 -> 0 | K120: =K204 -> 0 | L120: =L204 -> 0 | M120: =M204 -> 0 | N120: =N204 -> 0
D121: Long-Term Debt Financing (Payments) | J121: =J209 -> 0 | K121: =K209 -> 0 | L121: =L209 -> 0 | M121: =M209 -> 0 | N121: =N209 -> 0
D122: Net Cash Flow from Financing Activities | J122: =SUBTOTAL(9,OFFSET(J117,1,0):OFFSET(J122,-1,0)) -> 0 | K122: =SUBTOTAL(9,OFFSET(K117,1,0):OFFSET(K122,-1,0)) -> 0 | L122: =SUBTOTAL(9,OFFSET(L117,1,0):OFFSET(L122,-1,0)) -> 0 | M122: =SUBTOTAL(9,OFFSET(M117,1,0):OFFSET(M122,-1,0)) -> 0 | N122: =SUBTOTAL(9,OFFSET(N117,1,0):OFFSET(N122,-1,0)) -> 0
D124: Beginning Balance | J124: =OFFSET(J126,0,-1) -> 401556 | K124: =OFFSET(K126,0,-1) -> 210462.67 | L124: =OFFSET(L126,0,-1) -> 120513.86 | M124: =OFFSET(M126,0,-1) -> 70552.733 | N124: =OFFSET(N126,0,-1) -> 228742.56
...

Sheet DCF
B3: =Comp_Name -> Nu Scale | C3: | Discounted Cash Flow Analysis
B4: \
B6: WACC Assumptions
B8: Cost of Equity (CAPM) | H8: Current Share Price: | I8: =Current_Price -> 44.25
B9: 10 Year T-Bill Rate | C9: =Risk_Free_Rate -> 0.0409
B10: Equity Risk Premium | C10: =Equity_Risk_Premium -> 0.07
B11: Country Risk Premium | C11: =Country_RP -> 0.006
B12: Size Risk Premium | C12: =Size_RP -> 0
B13: Company Equity Beta | C13: =Equity_Beta -> 1.754
B14: CAPM Cost of Equity | C14: =Cost_of_Equity -> 0.174204
B16: Cost of Debt
B17: Assumed Effective Tax Rate | C17: =Tax_Rate -> 0.1737
B18: Debt Adjustment Factor | C18: =Debt_Adj_Factor -> 1.38
B19: After-Tax Cost of Debt | C19: =Cost_of_Debt -> 0.046638025
B21: WACC Calculation
B22: =Assumptions!$A$25 -> Equity Shares Outstanding (K) | C22: =Shares_Out -> 133890
B23: =Assumptions!$A$26 -> Company Capitalization ($K)
B24: Market Value of Equity | C24: =Equity_MV -> 5924632.5 | D24: =C24/C$26 -> 1
B25: Market Value of Debt | C25: =Debt_MV -> 0 | D25: =C25/C$26 -> 0
B26: Total Capitalization | C26: =Total_Capitalization -> 5924632.5 | D26: =D24+D25 -> 1
B27: WACC | D27: =IF(ISNUMBER(WACC_Override),WACC_Override,WACC) -> 0.174204 | K27: WACC Override:
B29: ="Discounted Cash Flows ($"&Scale_Symbol&")" -> Discounted Cash Flows ($K)
D30: Historic | E30: Projected
B31: Fiscal Year Ending | D31: =Financials!I6 -> 45657 | E31: =EOMONTH(D31,12) -> 46022 | F31: =EOMONTH(E31,12) -> 46387 | G31: =EOMONTH(F31,12) -> 46752 | H31: =EOMONTH(G31,12) -> 47118 | I31: =EOMONTH(H31,12) -> 47483
B33: Operating Income (EBIT) | D33: =INDEX(Financials!$24:$24,MATCH(D$31,Financials!$6:$6,0)) -> -138725 | E33: =INDEX(Financials!$24:$24,MATCH(E$31,Financials!$6:$6,0)) -> -137436.95 | F33: =INDEX(Financials!$24:$24,MATCH(F$31,Financials!$6:$6,0)) -> -124471.2 | G33: =INDEX(Financials!$24:$24,MATCH(G$31,Financials!$6:$6,0)) -> -66384.64 | H33: =INDEX(Financials!$24:$24,MATCH(H$31,Financials!$6:$6,0)) -> 58418.483 | I33: =INDEX(Financials!$24:$24,MATCH(I$31,Financials!$6:$6,0)) -> 131441.59
B34: Est. Cash Taxes | D34: =Financials!I39 -> 0 | E34: =Financials!J39 -> 0 | F34: =Financials!K39 -> 0 | G34: =Financials!L39 -> 0 | H34: =Financials!M39 -> 0 | I34: =Financials!N39 -> 0
B35: NOPAT* | D35: =D33+D34 -> -138725 | E35: =E33+E34 -> -137436.95 | F35: =F33+F34 -> -124471.2 | G35: =G33+G34 -> -66384.64 | H35: =H33+H34 -> 58418.483 | I35: =I33+I34 -> 131441.59
B36: Change in Working Capital (-) | D36: =INDEX(Financials!$109:$109,MATCH(D$31,Financials!$6:$6,0)) -> 0 | E36: =INDEX(Financials!$109:$109,MATCH(E$31,Financials!$6:$6,0)) -> -53055.574 | F36: =INDEX(Financials!$109:$109,MATCH(F$31,Financials!$6:$6,0)) -> 35611.175 | G36: =INDEX(Financials!$109:$109,MATCH(G$31,Financials!$6:$6,0)) -> 18700.362 | H36: =INDEX(Financials!$109:$109,MATCH(H$31,Financials!$6:$6,0)) -> 105934.91 | I36: =INDEX(Financials!$109:$109,MATCH(I$31,Financials!$6:$6,0)) -> 280186.54
B37: D&A (+) | D37: =INDEX(Financials!$110:$110,MATCH(D$31,Financials!$6:$6,0)) -> 0 | E37: =INDEX(Financials!$110:$110,MATCH(E$31,Financials!$6:$6,0)) -> 1431.0546 | F37: =INDEX(Financials!$110:$110,MATCH(F$31,Financials!$6:$6,0)) -> 2001.293 | G37: =INDEX(Financials!$110:$110,MATCH(G$31,Financials!$6:$6,0)) -> 3874.4597 | H37: =INDEX(Financials!$110:$110,MATCH(H$31,Financials!$6:$6,0)) -> 7647.6203 | I37: =INDEX(Financials!$110:$110,MATCH(I$31,Financials!$6:$6,0)) -> 13876.172
B38: Capex (-) | D38: =INDEX(Financials!$114:$114,MATCH(D$31,Financials!$6:$6,0)) -> 0 | E38: =INDEX(Financials!$114:$114,MATCH(E$31,Financials!$6:$6,0)) -> -2031.8652 | F38: =INDEX(Financials!$114:$114,MATCH(F$31,Financials!$6:$6,0)) -> -3090.0743 | G38: =INDEX(Financials!$114:$114,MATCH(G$31,Financials!$6:$6,0)) -> -6151.3084 | H38: =INDEX(Financials!$114:$114,MATCH(H$31,Financials!$6:$6,0)) -> -13811.179 | I38: =INDEX(Financials!$114:$114,MATCH(I$31,Financials!$6:$6,0)) -> -24564.23
B39: Free Cash Flow (FCFF) | D39: =SUM(D35:D38) -> -138725 | E39: =SUM(E35:E38) -> -191093.33 | F39: =SUM(F35:F38) -> -89948.807 | G39: =SUM(G35:G38) -> -49961.126 | H39: =SUM(H35:H38) -> 158189.83 | I39: =SUM(I35:I38) -> 400940.07
B40: Discount Factor | D40: =(1+$D$27)^D41 -> 1 | E40: =(1+$D$27)^E41 -> 1.0331002 | F40: =(1+$D$27)^F41 -> 1.2130704 | G40: =(1+$D$27)^G41 -> 1.4243921 | H40: =(1+$D$27)^H41 -> 1.6725269 | I40: =(1+$D$27)^I41 -> 1.9638878
B41: Discount Period | D41: 0 | E41: =YEARFRAC(TODAY(),E$31) -> 0.20277778 | F41: =E41+1 -> 1.2027778 | G41: =F41+1 -> 2.2027778 | H41: =G41+1 -> 3.2027778 | I41: =H41+1 -> 4.2027778
B43: Discounted Free Cash Flow | E43: =E39/E40 -> -184970.77 | F43: =F39/F40 -> -74149.702 | G43: =G39/G40 -> -35075.403 | H43: =H39/H40 -> 94581.338 | I43: =I39/I40 -> 204156.31
I44: *NOPAT = Net Operating Profit After Tax
B45: Perpetuity Growth Methodology | C45: Total | D45: per Share | J45: TV using Exit Multiple
B46: Perpetuity Growth Rate | C46: =Terminal_Rate -> 0.02 | J46: TV/Sales Multiple | K46: ='EV-Sales Multiples'!D29 -> 107.67238
B47: Terminal Value | C47: =K49 -> 36032172 | D47: =C47/Shares_Out -> 269.11772 | J47: Sales (FY 29) | K47: =Financials!N11 -> 657207.94
B48: Discounted Terminal Value | C48: =C47/I$40 -> 18347368 | D48: =C48/Shares_Out -> 137.03315 | J48: TV | K48: =K46*K47 -> 70763141
B49: Sum of DCFs | C49: =SUM(D$43:I$43) -> 4541.773 | D49: =C49/Shares_Out -> 0.033921675 | J49: PV | K49: =K48/I40 -> 36032172
B50: VOPS | C50: =C48+C49 -> 18351910 | D50: =D48+D49 -> 137.06707
B51: Net Non-Operating Assets (Liabilities) | C51: =SUMIF(BS_Start:BS_End,"NOA",OFFSET(BS_Start,0,MATCH($D$31,Financials!$6:$6,0)-COLUMN(BS_Start))) - SUMIF(BS_Start:BS_End,"NOL",OFFSET(BS_Start,0,MATCH($D$31,Financials!$6:$6,0)-COLUMN(BS_Start))) -> 43425 | D51: =C51/Shares_Out -> 0.32433341
B52: Enterprise Value | C52: =C50+C51 -> 18395335 | D52: =D50+D51 -> 137.3914
B53: Net Out: Financial Claims (Net of Cash) | C53: =SUMIF(BS_Start:BS_End,"Cash",OFFSET(BS_Start,0,MATCH($D$31,Financials!$6:$6,0)-COLUMN(BS_Start))) - SUMIF(BS_Start:BS_End,"FC",OFFSET(BS_Start,0,MATCH($D$31,Financials!$6:$6,0)-COLUMN(BS_Start))) -> 441556 | D53: =C53/Shares_Out -> 3.2979013
B54: Equity Value (Present Value) | C54: =C52+C53 -> 18836891 | D54: =C54/Shares_Out -> 140.6893
C56: Sensitivity Analysis: Perpetuity Growth Rate vs. WACC
B57: =$D$54 -> 140.6893 | C57: 0.01 | D57: =C57+0.5% -> 0.015 | E57: =Terminal_Rate -> 0.02 | F57: =E57+0.5% -> 0.025 | G57: =F57+0.5% -> 0.03 | H57: Perpetuity Growth Rate
B58: =B59-1% -> 0.144204 | C58: 9.8131138 | D58: 10.090757 | E58: 10.390753 | F58: 10.715916 | G58: 11.069552
B59: =B60-1% -> 0.154204 | C59: 9.117816 | D59: 9.3510462 | E59: 9.6016551 | F59: 9.8716604 | G59: 10.163405
B60: =B61-1% -> 0.164204 | C60: 8.5176953 | D60: 8.7156328 | E60: 8.9272964 | F60: 9.1541654 | G60: 9.3979391
B61: =WACC -> 0.174204 | C61: 7.9952005 | D61: 8.1646965 | E61: 8.3451842 | F61: 8.5377686 | G61: 8.7437079
B62: =B61+1% -> 0.184204 | C62: 7.5368171 | D62: 7.6831098 | E62: 7.8383116 | F62: 8.003262 | G62: 8.1789094
B63: =B62+1% -> 0.194204 | C63: 7.1319712 | D63: 7.2591275 | E63: 7.393583 | F63: 7.5359849 | G63: 7.687059
B64: =B63+1% -> 0.204204 | C64: 6.7722721 | D64: 6.8834931 | E64: 7.0007521 | F64: 7.1245544 | G64: 7.2554634
B65: WACC

Sheet DCF (H-Model for TV)
B3: =Comp_Name -> Nu Scale | C3: | Discounted Cash Flow Analysis
B6: WACC Assumptions
B8: Cost of Equity (CAPM) | H8: Current Share Price: | I8: =Current_Price -> 44.25
B9: 10 Year T-Bill Rate | C9: =Risk_Free_Rate -> 0.0409
B10: Equity Risk Premium | C10: =Equity_Risk_Premium -> 0.07
B11: Country Risk Premium | C11: =Country_RP -> 0.006
B12: Size Risk Premium | C12: =Size_RP -> 0
B13: Company Equity Beta | C13: =Equity_Beta -> 1.754
B14: CAPM Cost of Equity | C14: =Cost_of_Equity -> 0.174204
B16: Cost of Debt
B17: Assumed Effective Tax Rate | C17: =Tax_Rate -> 0.1737
B18: Debt Adjustment Factor | C18: =Debt_Adj_Factor -> 1.38
B19: After-Tax Cost of Debt | C19: =Cost_of_Debt -> 0.046638025
B21: WACC Calculation
B22: =Assumptions!$A$25 -> Equity Shares Outstanding (K) | C22: =Shares_Out -> 133890
B23: =Assumptions!$A$26 -> Company Capitalization ($K)
B24: Market Value of Equity | C24: =Equity_MV -> 5924632.5 | D24: =C24/C$26 -> 1
B25: Market Value of Debt | C25: =Debt_MV -> 0 | D25: =C25/C$26 -> 0
B26: Total Capitalization | C26: =Total_Capitalization -> 5924632.5 | D26: =D24+D25 -> 1
B27: WACC | D27: =IF(ISNUMBER(WACC_Override),WACC_Override,WACC) -> 0.174204 | K27: WACC Override:
B29: ="Discounted Cash Flows ($"&Scale_Symbol&")" -> Discounted Cash Flows ($K)
D30: Historic | E30: Projected
B31: Fiscal Year Ending | D31: =Financials!I6 -> 45657 | E31: =EOMONTH(D31,12) -> 46022 | F31: =EOMONTH(E31,12) -> 46387 | G31: =EOMONTH(F31,12) -> 46752 | H31: =EOMONTH(G31,12) -> 47118 | I31: =EOMONTH(H31,12) -> 47483
B33: Operating Income (EBIT) | D33: =INDEX(Financials!$24:$24,MATCH(D$31,Financials!$6:$6,0)) -> -138725 | E33: =INDEX(Financials!$24:$24,MATCH(E$31,Financials!$6:$6,0)) -> -137436.95 | F33: =INDEX(Financials!$24:$24,MATCH(F$31,Financials!$6:$6,0)) -> -124471.2 | G33: =INDEX(Financials!$24:$24,MATCH(G$31,Financials!$6:$6,0)) -> -66384.64 | H33: =INDEX(Financials!$24:$24,MATCH(H$31,Financials!$6:$6,0)) -> 58418.483 | I33: =INDEX(Financials!$24:$24,MATCH(I$31,Financials!$6:$6,0)) -> 131441.59
B34: Est. Cash Taxes | D34: =Financials!I39 -> 0 | E34: =Financials!J39 -> 0 | F34: =Financials!K39 -> 0 | G34: =Financials!L39 -> 0 | H34: =Financials!M39 -> 0 | I34: =Financials!N39 -> 0
B35: NOPAT* | D35: =D33+D34 -> -138725 | E35: =E33+E34 -> -137436.95 | F35: =F33+F34 -> -124471.2 | G35: =G33+G34 -> -66384.64 | H35: =H33+H34 -> 58418.483 | I35: =I33+I34 -> 131441.59
B36: Change in Working Capital (-) | D36: =INDEX(Financials!$109:$109,MATCH(D$31,Financials!$6:$6,0)) -> 0 | E36: =INDEX(Financials!$109:$109,MATCH(E$31,Financials!$6:$6,0)) -> -53055.574 | F36: =INDEX(Financials!$109:$109,MATCH(F$31,Financials!$6:$6,0)) -> 35611.175 | G36: =INDEX(Financials!$109:$109,MATCH(G$31,Financials!$6:$6,0)) -> 18700.362 | H36: =INDEX(Financials!$109:$109,MATCH(H$31,Financials!$6:$6,0)) -> 105934.91 | I36: =INDEX(Financials!$109:$109,MATCH(I$31,Financials!$6:$6,0)) -> 280186.54
B37: D&A (+) | D37: =INDEX(Financials!$110:$110,MATCH(D$31,Financials!$6:$6,0)) -> 0 | E37: =INDEX(Financials!$110:$110,MATCH(E$31,Financials!$6:$6,0)) -> 1431.0546 | F37: =INDEX(Financials!$110:$110,MATCH(F$31,Financials!$6:$6,0)) -> 2001.293 | G37: =INDEX(Financials!$110:$110,MATCH(G$31,Financials!$6:$6,0)) -> 3874.4597 | H37: =INDEX(Financials!$110:$110,MATCH(H$31,Financials!$6:$6,0)) -> 7647.6203 | I37: =INDEX(Financials!$110:$110,MATCH(I$31,Financials!$6:$6,0)) -> 13876.172
B38: Capex (-) | D38: =INDEX(Financials!$114:$114,MATCH(D$31,Financials!$6:$6,0)) -> 0 | E38: =INDEX(Financials!$114:$114,MATCH(E$31,Financials!$6:$6,0)) -> -2031.8652 | F38: =INDEX(Financials!$114:$114,MATCH(F$31,Financials!$6:$6,0)) -> -3090.0743 | G38: =INDEX(Financials!$114:$114,MATCH(G$31,Financials!$6:$6,0)) -> -6151.3084 | H38: =INDEX(Financials!$114:$114,MATCH(H$31,Financials!$6:$6,0)) -> -13811.179 | I38: =INDEX(Financials!$114:$114,MATCH(I$31,Financials!$6:$6,0)) -> -24564.23
B39: Free Cash Flow (FCFF) | D39: =SUM(D35:D38) -> -138725 | E39: =SUM(E35:E38) -> -191093.33 | F39: =SUM(F35:F38) -> -89948.807 | G39: =SUM(G35:G38) -> -49961.126 | H39: =SUM(H35:H38) -> 158189.83 | I39: =SUM(I35:I38) -> 400940.07
B40: Discount Factor | D40: =(1+$D$27)^D41 -> 1 | E40: =(1+$D$27)^E41 -> 1.0331002 | F40: =(1+$D$27)^F41 -> 1.2130704 | G40: =(1+$D$27)^G41 -> 1.4243921 | H40: =(1+$D$27)^H41 -> 1.6725269 | I40: =(1+$D$27)^I41 -> 1.9638878
B41: Discount Period | D41: 0 | E41: =YEARFRAC(TODAY(),E$31) -> 0.20277778 | F41: =E41+1 -> 1.2027778 | G41: =F41+1 -> 2.2027778 | H41: =G41+1 -> 3.2027778 | I41: =H41+1 -> 4.2027778
B43: Discounted Free Cash Flow | E43: =E39/E40 -> -184970.77 | F43: =F39/F40 -> -74149.702 | G43: =G39/G40 -> -35075.403 | H43: =H39/H40 -> 94581.338 | I43: =I39/I40 -> 204156.31
I44: *NOPAT = Net Operating Profit After Tax
B45: Perpetuity Growth Methodology | C45: Total | D45: per Share
B46: Initial High Growth Rate | C46: 0.05
B47: Life of High Growth Period | C47: 5
B48: Half Life of High Growth Period | C48: =IFERROR(C47/2,0) -> 2.5
B49: Perpetuity Growth Rate | C49: =Terminal_Rate -> 0.02
B50: Terminal Value | C50: =DCF!K49 -> 36032172 | D50: =C50/Shares_Out -> 269.11772
B51: Discounted Terminal Value | C51: =C50/I$40 -> 18347368 | D51: =C51/Shares_Out -> 137.03315
B52: Sum of DCFs | C52: =SUM(D$43:I$43) -> 4541.773 | D52: =C52/Shares_Out -> 0.033921675
B53: VOPS | C53: =C51+C52 -> 18351910 | D53: =D51+D52 -> 137.06707
B54: Net Non-Operating Assets (Liabilities) | C54: =SUMIF(BS_Start:BS_End,"NOA",OFFSET(BS_Start,0,MATCH($D$31,Financials!$6:$6,0)-COLUMN(BS_Start))) - SUMIF(BS_Start:BS_End,"NOL",OFFSET(BS_Start,0,MATCH($D$31,Financials!$6:$6,0)-COLUMN(BS_Start))) -> 43425 | D54: =C54/Shares_Out -> 0.32433341
B55: Enterprise Value | C55: =C53+C54 -> 18395335 | D55: =D53+D54 -> 137.3914
B56: Net Out: Financial Claims (Net of Cash) | C56: =SUMIF(BS_Start:BS_End,"Cash",OFFSET(BS_Start,0,MATCH($D$31,Financials!$6:$6,0)-COLUMN(BS_Start))) - SUMIF(BS_Start:BS_End,"FC",OFFSET(BS_Start,0,MATCH($D$31,Financials!$6:$6,0)-COLUMN(BS_Start))) -> 441556 | D56: =C56/Shares_Out -> 3.2979013
B57: Equity Value (Present Value) | C57: =C55+C56 -> 18836891 | D57: =C57/Shares_Out -> 140.6893
C59: Sensitivity Analysis: Perpetuity Growth Rate vs. WACC
B60: =$D$57 -> 140.6893 | C60: 0.01 | D60: =C60+0.5% -> 0.015 | E60: =Terminal_Rate -> 0.02 | F60: =E60+0.5% -> 0.025 | G60: =F60+0.5% -> 0.03 | H60: Perpetuity Growth Rate
B61: =B62-1% -> 0.144204 | C61: 10.440145 | D61: 10.660641 | E61: 10.898889 | F61: 11.157125 | G61: 11.437972
B62: =B63-1% -> 0.154204 | C62: 9.6803955 | D62: 9.8609843 | E62: 10.055029 | F62: 10.264093 | G62: 10.489989
B63: =B64-1% -> 0.164204 | C63: 9.0250473 | D63: 9.1744425 | E63: 9.3341976 | F63: 9.5054291 | G63: 9.6894196
B64: =WACC -> 0.174204 | C64: 8.4548215 | D64: 8.5794955 | E64: 8.7122545 | F64: 8.8539113 | G64: 9.0053914
B65: =B64+1% -> 0.184204 | C65: 7.9548751 | D65: 8.05972 | E65: 8.1709498 | F65: 8.2891663 | G65: 8.4150491
B66: =B65+1% -> 0.194204 | C66: 7.5135963 | D66: 7.6023662 | E66: 7.6962319 | F66: 7.7956451 | G66: 7.9011125
B67: =B66+1% -> 0.204204 | C67: 7.1217721 | D67: 7.1973872 | E67: 7.2771073 | F67: 7.3612759 | G67: 7.4502761
B68: WACC

Sheet P-S Multiples
A1: P/S Market Multiples
A3: Peer Group: | D3: =Comp_Name -> Nu Scale | G3: FCEL | J3: EOSE | M3: HYLN | Q3: Peer Group Average
B5: Year | D5: Low | E5: High | G5: Low | H5: High | J5: Low | K5: High | M5: Low | N5: High | Q5: Low | R5: High
A7: Market Price | B7: {=INDEX(Annual_Periods,1)} -> 44560 | D7: 8.56 | E7: 11.72 | G7: 153.3015 | H7: 838.81 | J7: 7.52 | K7: 30.44 | M7: 5.82 | N7: 20.78 | Q7: =AVERAGE(D7, G7, J7, M7) -> 43.800375 | R7: =AVERAGE(E7, H7, K7, N7) -> 225.4375
B8: =EOMONTH(B7,12) -> 44926 | D8: 8.96 | E8: 15.32 | G8: 76.5 | H8: 208.2021 | J8: 0.97 | K8: 7.6 | M8: 2.19 | N8: 6.28 | Q8: =AVERAGE(D8, G8, J8, M8) -> 22.155 | R8: =AVERAGE(E8, H8, K8, N8) -> 59.350525
B9: =EOMONTH(B8,12) -> 45291 | D9: 2.08 | E9: 11.06 | G9: 30.9003 | H9: 127.5013 | J9: 1.02 | K9: 5.03 | M9: 0.541 | N9: 3.74 | Q9: =AVERAGE(D9, G9, J9, M9) -> 8.635325 | R9: =AVERAGE(E9, H9, K9, N9) -> 36.832825
B10: =EOMONTH(B9,12) -> 45657 | D10: 1.92 | E10: 30.21 | G10: 5.7 | H10: 46.2 | J10: 0.6447 | K10: 5.17 | M10: 0.8137 | N10: 3.84 | Q10: =AVERAGE(D10, G10, J10, M10) -> 2.2696 | R10: =AVERAGE(E10, H10, K10, N10) -> 21.355
A12: Sales (per Share) | B12: =B7 -> 44560 | D12: 0.1 | G12: 6.24 | J12: 0.09 | M12: 6.66 | Q12: =AVERAGE(D12, G12, J12, M12) -> 3.2725
B13: =B8 -> 44926 | D13: 0.23 | G13: 10.22 | J13: 0.29 | M13: 11.3 | Q13: =AVERAGE(D13, G13, J13, M13) -> 5.51
B14: =B9 -> 45291 | D14: 0.31 | G14: 8.82 | J14: 0.13 | M14: 11.72 | Q14: =AVERAGE(D14, G14, J14, M14) -> 5.245
B15: =B10 -> 45657 | D15: 0.4 | G15: 6.73 | J15: 0.07 | M15: 10.87 | Q15: =AVERAGE(D15, G15, J15, M15) -> 4.5175
A17: P/S Ratio | B17: =B7 -> 44560 | D17: =IFERROR(IF(INDEX(D$7:D$10,MATCH($B17,$B$7:$B$10,0))/INDEX(D$12:D$15,MATCH($B17,$B$12:$B$15,0))<0,"NM",INDEX(D$7:D$10,MATCH($B17,$B$7:$B$10,0))/INDEX(D$12:D$15,MATCH($B17,$B$12:$B$15,0))),"NA") -> 85.6 | E17: =IFERROR(IF(INDEX(E$7:E$10,MATCH($B17,$B$7:$B$10,0))/INDEX(D$12:D$15,MATCH($B17,$B$12:$B$15,0))<0,"NM",INDEX(E$7:E$10,MATCH($B17,$B$7:$B$10,0))/INDEX(D$12:D$15,MATCH($B17,$B$12:$B$15,0))),"NA") -> 117.2 | G17: =IFERROR(IF(INDEX(G$7:G$10,MATCH($B17,$B$7:$B$10,0))/INDEX(G$12:G$15,MATCH($B17,$B$12:$B$15,0))<0,"NM",INDEX(G$7:G$10,MATCH($B17,$B$7:$B$10,0))/INDEX(G$12:G$15,MATCH($B17,$B$12:$B$15,0))),"NA") -> 24.567548 | H17: =IFERROR(IF(INDEX(H$7:H$10,MATCH($B17,$B$7:$B$10,0))/INDEX(G$12:G$15,MATCH($B17,$B$12:$B$15,0))<0,"NM",INDEX(H$7:H$10,MATCH($B17,$B$7:$B$10,0))/INDEX(G$12:G$15,MATCH($B17,$B$12:$B$15,0))),"NA") -> 134.42468 | J17: =IFERROR(IF(INDEX(J$7:J$10,MATCH($B17,$B$7:$B$10,0))/INDEX(J$12:J$15,MATCH($B17,$B$12:$B$15,0))<0,"NM",INDEX(J$7:J$10,MATCH($B17,$B$7:$B$10,0))/INDEX(J$12:J$15,MATCH($B17,$B$12:$B$15,0))),"NA") -> 83.555556 | K17: =IFERROR(IF(INDEX(K$7:K$10,MATCH($B17,$B$7:$B$10,0))/INDEX(J$12:J$15,MATCH($B17,$B$12:$B$15,0))<0,"NM",INDEX(K$7:K$10,MATCH($B17,$B$7:$B$10,0))/INDEX(J$12:J$15,MATCH($B17,$B$12:$B$15,0))),"NA") -> 338.22222 | M17: =IFERROR(IF(INDEX(M$7:M$10,MATCH($B17,$B$7:$B$10,0))/INDEX(M$12:M$15,MATCH($B17,$B$12:$B$15,0))<0,"NM",INDEX(M$7:M$10,MATCH($B17,$B$7:$B$10,0))/INDEX(M$12:M$15,MATCH($B17,$B$12:$B$15,0))),"NA") -> 0.87387387 | N17: =IFERROR(IF(INDEX(N$7:N$10,MATCH($B17,$B$7:$B$10,0))/INDEX(M$12:M$15,MATCH($B17,$B$12:$B$15,0))<0,"NM",INDEX(N$7:N$10,MATCH($B17,$B$7:$B$10,0))/INDEX(M$12:M$15,MATCH($B17,$B$12:$B$15,0))),"NA") -> 3.1201201 | Q17: =IFERROR(AVERAGE(G17,J17,M17),"NA") -> 36.332326 | R17: =IFERROR(AVERAGE(H17,K17,N17),"NA") -> 158.58901 | T17: =IFERROR(AVERAGE(J17,M17,Q17),"NA") -> 40.253918 | U17: =IFERROR(AVERAGE(K17,N17,R17),"NA") -> 166.64378
B18: =B8 -> 44926 | D18: =IFERROR(IF(INDEX(D$7:D$10,MATCH($B18,$B$7:$B$10,0))/INDEX(D$12:D$15,MATCH($B18,$B$12:$B$15,0))<0,"NM",INDEX(D$7:D$10,MATCH($B18,$B$7:$B$10,0))/INDEX(D$12:D$15,MATCH($B18,$B$12:$B$15,0))),"NA") -> 38.956522 | E18: =IFERROR(IF(INDEX(E$7:E$10,MATCH($B18,$B$7:$B$10,0))/INDEX(D$12:D$15,MATCH($B18,$B$12:$B$15,0))<0,"NM",INDEX(E$7:E$10,MATCH($B18,$B$7:$B$10,0))/INDEX(D$12:D$15,MATCH($B18,$B$12:$B$15,0))),"NA") -> 66.608696 | G18: =IFERROR(IF(INDEX(G$7:G$10,MATCH($B18,$B$7:$B$10,0))/INDEX(G$12:G$15,MATCH($B18,$B$12:$B$15,0))<0,"NM",INDEX(G$7:G$10,MATCH($B18,$B$7:$B$10,0))/INDEX(G$12:G$15,MATCH($B18,$B$12:$B$15,0))),"NA") -> 7.4853229 | H18: =IFERROR(IF(INDEX(H$7:H$10,MATCH($B18,$B$7:$B$10,0))/INDEX(G$12:G$15,MATCH($B18,$B$12:$B$15,0))<0,"NM",INDEX(H$7:H$10,MATCH($B18,$B$7:$B$10,0))/INDEX(G$12:G$15,MATCH($B18,$B$12:$B$15,0))),"NA") -> 20.372025 | J18: =IFERROR(IF(INDEX(J$7:J$10,MATCH($B18,$B$7:$B$10,0))/INDEX(J$12:J$15,MATCH($B18,$B$12:$B$15,0))<0,"NM",INDEX(J$7:J$10,MATCH($B18,$B$7:$B$10,0))/INDEX(J$12:J$15,MATCH($B18,$B$12:$B$15,0))),"NA") -> 3.3448276 | K18: =IFERROR(IF(INDEX(K$7:K$10,MATCH($B18,$B$7:$B$10,0))/INDEX(J$12:J$15,MATCH($B18,$B$12:$B$15,0))<0,"NM",INDEX(K$7:K$10,MATCH($B18,$B$7:$B$10,0))/INDEX(J$12:J$15,MATCH($B18,$B$12:$B$15,0))),"NA") -> 26.206897 | M18: =IFERROR(IF(INDEX(M$7:M$10,MATCH($B18,$B$7:$B$10,0))/INDEX(M$12:M$15,MATCH($B18,$B$12:$B$15,0))<0,"NM",INDEX(M$7:M$10,MATCH($B18,$B$7:$B$10,0))/INDEX(M$12:M$15,MATCH($B18,$B$12:$B$15,0))),"NA") -> 0.19380531 | N18: =IFERROR(IF(INDEX(N$7:N$10,MATCH($B18,$B$7:$B$10,0))/INDEX(M$12:M$15,MATCH($B18,$B$12:$B$15,0))<0,"NM",INDEX(N$7:N$10,MATCH($B18,$B$7:$B$10,0))/INDEX(M$12:M$15,MATCH($B18,$B$12:$B$15,0))),"NA") -> 0.55575221 | Q18: =IFERROR(AVERAGE(G18,J18,M18),"NA") -> 3.6746519 | R18: =IFERROR(AVERAGE(H18,K18,N18),"NA") -> 15.711558 | T18: =IFERROR(AVERAGE(J18,M18,Q18),"NA") -> 2.4044283 | U18: =IFERROR(AVERAGE(K18,N18,R18),"NA") -> 14.158069
B19: =B9 -> 45291 | D19: =IFERROR(IF(INDEX(D$7:D$10,MATCH($B19,$B$7:$B$10,0))/INDEX(D$12:D$15,MATCH($B19,$B$12:$B$15,0))<0,"NM",INDEX(D$7:D$10,MATCH($B19,$B$7:$B$10,0))/INDEX(D$12:D$15,MATCH($B19,$B$12:$B$15,0))),"NA") -> 6.7096774 | E19: =IFERROR(IF(INDEX(E$7:E$10,MATCH($B19,$B$7:$B$10,0))/INDEX(D$12:D$15,MATCH($B19,$B$12:$B$15,0))<0,"NM",INDEX(E$7:E$10,MATCH($B19,$B$7:$B$10,0))/INDEX(D$12:D$15,MATCH($B19,$B$12:$B$15,0))),"NA") -> 35.677419 | G19: =IFERROR(IF(INDEX(G$7:G$10,MATCH($B19,$B$7:$B$10,0))/INDEX(G$12:G$15,MATCH($B19,$B$12:$B$15,0))<0,"NM",INDEX(G$7:G$10,MATCH($B19,$B$7:$B$10,0))/INDEX(G$12:G$15,MATCH($B19,$B$12:$B$15,0))),"NA") -> 3.5034354 | H19: =IFERROR(IF(INDEX(H$7:H$10,MATCH($B19,$B$7:$B$10,0))/INDEX(G$12:G$15,MATCH($B19,$B$12:$B$15,0))<0,"NM",INDEX(H$7:H$10,MATCH($B19,$B$7:$B$10,0))/INDEX(G$12:G$15,MATCH($B19,$B$12:$B$15,0))),"NA") -> 14.45593 | J19: =IFERROR(IF(INDEX(J$7:J$10,MATCH($B19,$B$7:$B$10,0))/INDEX(J$12:J$15,MATCH($B19,$B$12:$B$15,0))<0,"NM",INDEX(J$7:J$10,MATCH($B19,$B$7:$B$10,0))/INDEX(J$12:J$15,MATCH($B19,$B$12:$B$15,0))),"NA") -> 7.8461538 | K19: =IFERROR(IF(INDEX(K$7:K$10,MATCH($B19,$B$7:$B$10,0))/INDEX(J$12:J$15,MATCH($B19,$B$12:$B$15,0))<0,"NM",INDEX(K$7:K$10,MATCH($B19,$B$7:$B$10,0))/INDEX(J$12:J$15,MATCH($B19,$B$12:$B$15,0))),"NA") -> 38.692308 | M19: =IFERROR(IF(INDEX(M$7:M$10,MATCH($B19,$B$7:$B$10,0))/INDEX(M$12:M$15,MATCH($B19,$B$12:$B$15,0))<0,"NM",INDEX(M$7:M$10,MATCH($B19,$B$7:$B$10,0))/INDEX(M$12:M$15,MATCH($B19,$B$12:$B$15,0))),"NA") -> 0.04616041 | N19: =IFERROR(IF(INDEX(N$7:N$10,MATCH($B19,$B$7:$B$10,0))/INDEX(M$12:M$15,MATCH($B19,$B$12:$B$15,0))<0,"NM",INDEX(N$7:N$10,MATCH($B19,$B$7:$B$10,0))/INDEX(M$12:M$15,MATCH($B19,$B$12:$B$15,0))),"NA") -> 0.31911263 | Q19: =IFERROR(AVERAGE(G19,J19,M19),"NA") -> 3.7985832 | R19: =IFERROR(AVERAGE(H19,K19,N19),"NA") -> 17.82245 | T19: =IFERROR(AVERAGE(J19,M19,Q19),"NA") -> 3.8969658 | U19: =IFERROR(AVERAGE(K19,N19,R19),"NA") -> 18.944623
B20: =B10 -> 45657 | D20: =IFERROR(IF(INDEX(D$7:D$10,MATCH($B20,$B$7:$B$10,0))/INDEX(D$12:D$15,MATCH($B20,$B$12:$B$15,0))<0,"NM",INDEX(D$7:D$10,MATCH($B20,$B$7:$B$10,0))/INDEX(D$12:D$15,MATCH($B20,$B$12:$B$15,0))),"NA") -> 4.8 | E20: =IFERROR(IF(INDEX(E$7:E$10,MATCH($B20,$B$7:$B$10,0))/INDEX(D$12:D$15,MATCH($B20,$B$12:$B$15,0))<0,"NM",INDEX(E$7:E$10,MATCH($B20,$B$7:$B$10,0))/INDEX(D$12:D$15,MATCH($B20,$B$12:$B$15,0))),"NA") -> 75.525 | G20: =IFERROR(IF(INDEX(G$7:G$10,MATCH($B20,$B$7:$B$10,0))/INDEX(G$12:G$15,MATCH($B20,$B$12:$B$15,0))<0,"NM",INDEX(G$7:G$10,MATCH($B20,$B$7:$B$10,0))/INDEX(G$12:G$15,MATCH($B20,$B$12:$B$15,0))),"NA") -> 0.84695394 | H20: =IFERROR(IF(INDEX(H$7:H$10,MATCH($B20,$B$7:$B$10,0))/INDEX(G$12:G$15,MATCH($B20,$B$12:$B$15,0))<0,"NM",INDEX(H$7:H$10,MATCH($B20,$B$7:$B$10,0))/INDEX(G$12:G$15,MATCH($B20,$B$12:$B$15,0))),"NA") -> 6.8647845 | J20: =IFERROR(IF(INDEX(J$7:J$10,MATCH($B20,$B$7:$B$10,0))/INDEX(J$12:J$15,MATCH($B20,$B$12:$B$15,0))<0,"NM",INDEX(J$7:J$10,MATCH($B20,$B$7:$B$10,0))/INDEX(J$12:J$15,MATCH($B20,$B$12:$B$15,0))),"NA") -> 9.21 | K20: =IFERROR(IF(INDEX(K$7:K$10,MATCH($B20,$B$7:$B$10,0))/INDEX(J$12:J$15,MATCH($B20,$B$12:$B$15,0))<0,"NM",INDEX(K$7:K$10,MATCH($B20,$B$7:$B$10,0))/INDEX(J$12:J$15,MATCH($B20,$B$12:$B$15,0))),"NA") -> 73.857143 | M20: =IFERROR(IF(INDEX(M$7:M$10,MATCH($B20,$B$7:$B$10,0))/INDEX(M$12:M$15,MATCH($B20,$B$12:$B$15,0))<0,"NM",INDEX(M$7:M$10,MATCH($B20,$B$7:$B$10,0))/INDEX(M$12:M$15,MATCH($B20,$B$12:$B$15,0))),"NA") -> 0.074857406 | N20: =IFERROR(IF(INDEX(N$7:N$10,MATCH($B20,$B$7:$B$10,0))/INDEX(M$12:M$15,MATCH($B20,$B$12:$B$15,0))<0,"NM",INDEX(N$7:N$10,MATCH($B20,$B$7:$B$10,0))/INDEX(M$12:M$15,MATCH($B20,$B$12:$B$15,0))),"NA") -> 0.35326587 | Q20: =IFERROR(AVERAGE(G20,J20,M20),"NA") -> 3.3772704 | R20: =IFERROR(AVERAGE(H20,K20,N20),"NA") -> 27.025064 | T20: =IFERROR(AVERAGE(J20,M20,Q20),"NA") -> 4.2207093 | U20: =IFERROR(AVERAGE(K20,N20,R20),"NA") -> 33.745158
B21: Average | D21: =IFERROR(AVERAGE(D17:D20),"NA") -> 34.01655 | E21: =IFERROR(AVERAGE(E17:E20),"NA") -> 73.752779 | G21: =IFERROR(AVERAGE(G17:G20),"NA") -> 9.1008151 | H21: =IFERROR(AVERAGE(H17:H20),"NA") -> 44.029355 | J21: =IFERROR(AVERAGE(J17:J20),"NA") -> 25.989134 | K21: =IFERROR(AVERAGE(K17:K20),"NA") -> 119.24464 | M21: =IFERROR(AVERAGE(M17:M20),"NA") -> 0.29717425 | N21: =IFERROR(AVERAGE(N17:N20),"NA") -> 1.0870627 | Q21: =IFERROR(AVERAGE(Q17:Q20),"NA") -> 11.795708 | R21: =IFERROR(AVERAGE(R17:R20),"NA") -> 54.78702 | T21: =IFERROR(AVERAGE(T17:T20),"NA") -> 12.694005 | U21: =IFERROR(AVERAGE(U17:U20),"NA") -> 58.372908
A23: Discount Applied | G23: 0 | J23: 0 | M23: 0 | Q23: =AVERAGE(G21*(1-G23),M21*(1-M23),J21*(1-J23)) -> 11.795708 | R23: =AVERAGE(H21*(1-G23),N21*(1-M23),K21*(1-J23)) -> 54.78702
A25: Using Historical Averages
A26: Historical Peer Group Hi-Low Avg. | D26: =AVERAGE($Q$23:$R$23) -> 33.291364
A27: Historical Target Firm Hi-Low Avg. | D27: =AVERAGE($D$21:$E$21) -> 53.884664 | G27: =AVERAGE(G21:H21) -> 26.565085 | I27: =AVERAGE(I21:J21) -> 25.989134 | O27: =AVERAGE(O21:O21) -> #DIV/0!
A29: Average P/S | D29: =AVERAGE(D27,D26) -> 43.588014
A30: Projected Forward Sales per Share | D30: =Financials!J11/Assumptions!B25 -> 0.38735529
A32: Relative P/S Target Price | D32: =D29*D30 -> 16.884048
A34: Helpful Notes:
A35: Check the note in the cell "Historical Relative P/E" on the top left corner in Yellow
A36: Be sure to check your data for outliers that may be skewing the results of the model and delete them.
A37: If you are not sure about a value, consult your SM

Sheet Market Cap-Sales Multiples
A1: EV/Sales Market Multiples Model
A3: Peer Group: | D3: =Comp_Name -> Nu Scale | G3: FCEL | J3: EOSE | M3: HYLN | Q3: Peer Group Average
B5: Year | D5: Low | E5: High | G5: Low | H5: High | J5: Low | K5: High | M5: Low | N5: High | Q5: Low | R5: High
A7: Market Cap | B7: {=INDEX(Annual_Periods,1)} -> 44560 | D7: 246100 | E7: 336950 | G7: 1799524.2 | H7: 9014649.1 | J7: 403815.3 | K7: 1516324.4 | M7: 98889.1 | N7: 3198080 | Q7: =AVERAGE(D7, G7, J7, M7) -> 637082.15 | R7: =AVERAGE(E7, H7, K7, N7) -> 3516500.9
B8: =EOMONTH(B7,12) -> 44926 | D8: 271687 | E8: 3384056.5 | G8: 1034593.9 | H8: 2544813.1 | J8: 60979.2 | K8: 408111.2 | M8: 393573.9 | N8: 1088408.3 | Q8: =AVERAGE(D8, G8, J8, M8) -> 440208.5 | R8: =AVERAGE(E8, H8, K8, N8) -> 1856347.3
B9: =EOMONTH(B8,12) -> 45291 | D9: 481510.7 | E9: 2497188.6 | G9: 464145.1 | H9: 1724323.1 | J9: 104886.2 | K9: 639707.7 | M9: 98889.1 | N9: 672130.8 | Q9: =AVERAGE(D9, G9, J9, M9) -> 287357.78 | R9: =AVERAGE(E9, H9, K9, N9) -> 1383337.6
B10: =EOMONTH(B9,12) -> 45657 | D10: 444157.5 | E10: 7720523.4 | G10: 116142.9 | H10: 671720.6 | J10: 130864 | K10: 1126607 | M10: 148735.8 | N10: 667140.2 | Q10: =AVERAGE(D10, G10, J10, M10) -> 209975.05 | R10: =AVERAGE(E10, H10, K10, N10) -> 2546497.8
A12: Annual Sales | B12: =B7 -> 44560 | D12: =Financials!F11 -> 2862 | G12: 69585 | J12: 4598 | M12: 200 | Q12: =AVERAGE(D12, G12, J12, M12) -> 19311.25
B13: =B8 -> 44926 | D13: =Financials!G11 -> 11804 | G13: 130484 | J13: 17924 | M13: 2106 | Q13: =AVERAGE(D13, G13, J13, M13) -> 40579.5
B14: =B9 -> 45291 | D14: =Financials!H11 -> 22810 | G14: 123394 | J14: 16378 | M14: 672 | Q14: =AVERAGE(D14, G14, J14, M14) -> 40813.5
B15: =B10 -> 45657 | D15: =Financials!I11 -> 37045 | G15: 112132 | J15: 15606 | M15: 1509 | Q15: =AVERAGE(D15, G15, J15, M15) -> 41573
A17: EV/Sales Ratio | B17: =B7 -> 44560 | D17: =IFERROR(IF(INDEX(D$7:D$10,MATCH($B17,$B$7:$B$10,0))/INDEX(D$12:D$15,MATCH($B17,$B$12:$B$15,0))<0,"NM",INDEX(D$7:D$10,MATCH($B17,$B$7:$B$10,0))/INDEX(D$12:D$15,MATCH($B17,$B$12:$B$15,0))),"NA") -> 85.988819 | E17: =IFERROR(IF(INDEX(E$7:E$10,MATCH($B17,$B$7:$B$10,0))/INDEX(D$12:D$15,MATCH($B17,$B$12:$B$15,0))<0,"NM",INDEX(E$7:E$10,MATCH($B17,$B$7:$B$10,0))/INDEX(D$12:D$15,MATCH($B17,$B$12:$B$15,0))),"NA") -> 117.73235 | G17: =IFERROR(IF(INDEX(G$7:G$10,MATCH($B17,$B$7:$B$10,0))/INDEX(G$12:G$15,MATCH($B17,$B$12:$B$15,0))<0,"NM",INDEX(G$7:G$10,MATCH($B17,$B$7:$B$10,0))/INDEX(G$12:G$15,MATCH($B17,$B$12:$B$15,0))),"NA") -> 25.860806 | H17: =IFERROR(IF(INDEX(H$7:H$10,MATCH($B17,$B$7:$B$10,0))/INDEX(G$12:G$15,MATCH($B17,$B$12:$B$15,0))<0,"NM",INDEX(H$7:H$10,MATCH($B17,$B$7:$B$10,0))/INDEX(G$12:G$15,MATCH($B17,$B$12:$B$15,0))),"NA") -> 129.54874 | J17: =IFERROR(IF(INDEX(J$7:J$10,MATCH($B17,$B$7:$B$10,0))/INDEX(J$12:J$15,MATCH($B17,$B$12:$B$15,0))<0,"NM",INDEX(J$7:J$10,MATCH($B17,$B$7:$B$10,0))/INDEX(J$12:J$15,MATCH($B17,$B$12:$B$15,0))),"NA") -> 87.824119 | K17: =IFERROR(IF(INDEX(K$7:K$10,MATCH($B17,$B$7:$B$10,0))/INDEX(J$12:J$15,MATCH($B17,$B$12:$B$15,0))<0,"NM",INDEX(K$7:K$10,MATCH($B17,$B$7:$B$10,0))/INDEX(J$12:J$15,MATCH($B17,$B$12:$B$15,0))),"NA") -> 329.77912 | M17: NM | N17: NM | Q17: =IFERROR(AVERAGE(G17,J17,M17),"NA") -> 56.842463 | R17: =IFERROR(AVERAGE(H17,K17,N17),"NA") -> 229.66393
B18: =B8 -> 44926 | D18: =IFERROR(IF(INDEX(D$7:D$10,MATCH($B18,$B$7:$B$10,0))/INDEX(D$12:D$15,MATCH($B18,$B$12:$B$15,0))<0,"NM",INDEX(D$7:D$10,MATCH($B18,$B$7:$B$10,0))/INDEX(D$12:D$15,MATCH($B18,$B$12:$B$15,0))),"NA") -> 23.01652 | E18: =IFERROR(IF(INDEX(E$7:E$10,MATCH($B18,$B$7:$B$10,0))/INDEX(D$12:D$15,MATCH($B18,$B$12:$B$15,0))<0,"NM",INDEX(E$7:E$10,MATCH($B18,$B$7:$B$10,0))/INDEX(D$12:D$15,MATCH($B18,$B$12:$B$15,0))),"NA") -> 286.68727 | G18: =IFERROR(IF(INDEX(G$7:G$10,MATCH($B18,$B$7:$B$10,0))/INDEX(G$12:G$15,MATCH($B18,$B$12:$B$15,0))<0,"NM",INDEX(G$7:G$10,MATCH($B18,$B$7:$B$10,0))/INDEX(G$12:G$15,MATCH($B18,$B$12:$B$15,0))),"NA") -> 7.9288947 | H18: =IFERROR(IF(INDEX(H$7:H$10,MATCH($B18,$B$7:$B$10,0))/INDEX(G$12:G$15,MATCH($B18,$B$12:$B$15,0))<0,"NM",INDEX(H$7:H$10,MATCH($B18,$B$7:$B$10,0))/INDEX(G$12:G$15,MATCH($B18,$B$12:$B$15,0))),"NA") -> 19.502875 | J18: =IFERROR(IF(INDEX(J$7:J$10,MATCH($B18,$B$7:$B$10,0))/INDEX(J$12:J$15,MATCH($B18,$B$12:$B$15,0))<0,"NM",INDEX(J$7:J$10,MATCH($B18,$B$7:$B$10,0))/INDEX(J$12:J$15,MATCH($B18,$B$12:$B$15,0))),"NA") -> 3.4020977 | K18: =IFERROR(IF(INDEX(K$7:K$10,MATCH($B18,$B$7:$B$10,0))/INDEX(J$12:J$15,MATCH($B18,$B$12:$B$15,0))<0,"NM",INDEX(K$7:K$10,MATCH($B18,$B$7:$B$10,0))/INDEX(J$12:J$15,MATCH($B18,$B$12:$B$15,0))),"NA") -> 22.76898 | M18: =IFERROR(IF(INDEX(M$7:M$10,MATCH($B18,$B$7:$B$10,0))/INDEX(M$12:M$15,MATCH($B18,$B$12:$B$15,0))<0,"NM",INDEX(M$7:M$10,MATCH($B18,$B$7:$B$10,0))/INDEX(M$12:M$15,MATCH($B18,$B$12:$B$15,0))),"NA") -> 186.88219 | N18: =IFERROR(IF(INDEX(N$7:N$10,MATCH($B18,$B$7:$B$10,0))/INDEX(M$12:M$15,MATCH($B18,$B$12:$B$15,0))<0,"NM",INDEX(N$7:N$10,MATCH($B18,$B$7:$B$10,0))/INDEX(M$12:M$15,MATCH($B18,$B$12:$B$15,0))),"NA") -> 516.81306 | Q18: =IFERROR(AVERAGE(G18,J18,M18),"NA") -> 66.071062 | R18: =IFERROR(AVERAGE(H18,K18,N18),"NA") -> 186.36164
B19: =B9 -> 45291 | D19: =IFERROR(IF(INDEX(D$7:D$10,MATCH($B19,$B$7:$B$10,0))/INDEX(D$12:D$15,MATCH($B19,$B$12:$B$15,0))<0,"NM",INDEX(D$7:D$10,MATCH($B19,$B$7:$B$10,0))/INDEX(D$12:D$15,MATCH($B19,$B$12:$B$15,0))),"NA") -> 21.109632 | E19: =IFERROR(IF(INDEX(E$7:E$10,MATCH($B19,$B$7:$B$10,0))/INDEX(D$12:D$15,MATCH($B19,$B$12:$B$15,0))<0,"NM",INDEX(E$7:E$10,MATCH($B19,$B$7:$B$10,0))/INDEX(D$12:D$15,MATCH($B19,$B$12:$B$15,0))),"NA") -> 109.4778 | G19: =IFERROR(IF(INDEX(G$7:G$10,MATCH($B19,$B$7:$B$10,0))/INDEX(G$12:G$15,MATCH($B19,$B$12:$B$15,0))<0,"NM",INDEX(G$7:G$10,MATCH($B19,$B$7:$B$10,0))/INDEX(G$12:G$15,MATCH($B19,$B$12:$B$15,0))),"NA") -> 3.7614884 | H19: =IFERROR(IF(INDEX(H$7:H$10,MATCH($B19,$B$7:$B$10,0))/INDEX(G$12:G$15,MATCH($B19,$B$12:$B$15,0))<0,"NM",INDEX(H$7:H$10,MATCH($B19,$B$7:$B$10,0))/INDEX(G$12:G$15,MATCH($B19,$B$12:$B$15,0))),"NA") -> 13.974124 | J19: =IFERROR(IF(INDEX(J$7:J$10,MATCH($B19,$B$7:$B$10,0))/INDEX(J$12:J$15,MATCH($B19,$B$12:$B$15,0))<0,"NM",INDEX(J$7:J$10,MATCH($B19,$B$7:$B$10,0))/INDEX(J$12:J$15,MATCH($B19,$B$12:$B$15,0))),"NA") -> 6.4040909 | K19: =IFERROR(IF(INDEX(K$7:K$10,MATCH($B19,$B$7:$B$10,0))/INDEX(J$12:J$15,MATCH($B19,$B$12:$B$15,0))<0,"NM",INDEX(K$7:K$10,MATCH($B19,$B$7:$B$10,0))/INDEX(J$12:J$15,MATCH($B19,$B$12:$B$15,0))),"NA") -> 39.058963 | M19: =IFERROR(IF(INDEX(M$7:M$10,MATCH($B19,$B$7:$B$10,0))/INDEX(M$12:M$15,MATCH($B19,$B$12:$B$15,0))<0,"NM",INDEX(M$7:M$10,MATCH($B19,$B$7:$B$10,0))/INDEX(M$12:M$15,MATCH($B19,$B$12:$B$15,0))),"NA") -> 147.1564 | N19: =IFERROR(IF(INDEX(N$7:N$10,MATCH($B19,$B$7:$B$10,0))/INDEX(M$12:M$15,MATCH($B19,$B$12:$B$15,0))<0,"NM",INDEX(N$7:N$10,MATCH($B19,$B$7:$B$10,0))/INDEX(M$12:M$15,MATCH($B19,$B$12:$B$15,0))),"NA") -> 1000.1946 | Q19: =IFERROR(AVERAGE(G19,J19,M19),"NA") -> 52.440659 | R19: =IFERROR(AVERAGE(H19,K19,N19),"NA") -> 351.07591
B20: =B10 -> 45657 | D20: =IFERROR(IF(INDEX(D$7:D$10,MATCH($B20,$B$7:$B$10,0))/INDEX(D$12:D$15,MATCH($B20,$B$12:$B$15,0))<0,"NM",INDEX(D$7:D$10,MATCH($B20,$B$7:$B$10,0))/INDEX(D$12:D$15,MATCH($B20,$B$12:$B$15,0))),"NA") -> 11.989675 | E20: =IFERROR(IF(INDEX(E$7:E$10,MATCH($B20,$B$7:$B$10,0))/INDEX(D$12:D$15,MATCH($B20,$B$12:$B$15,0))<0,"NM",INDEX(E$7:E$10,MATCH($B20,$B$7:$B$10,0))/INDEX(D$12:D$15,MATCH($B20,$B$12:$B$15,0))),"NA") -> 208.40932 | G20: =IFERROR(IF(INDEX(G$7:G$10,MATCH($B20,$B$7:$B$10,0))/INDEX(G$12:G$15,MATCH($B20,$B$12:$B$15,0))<0,"NM",INDEX(G$7:G$10,MATCH($B20,$B$7:$B$10,0))/INDEX(G$12:G$15,MATCH($B20,$B$12:$B$15,0))),"NA") -> 1.0357695 | H20: =IFERROR(IF(INDEX(H$7:H$10,MATCH($B20,$B$7:$B$10,0))/INDEX(G$12:G$15,MATCH($B20,$B$12:$B$15,0))<0,"NM",INDEX(H$7:H$10,MATCH($B20,$B$7:$B$10,0))/INDEX(G$12:G$15,MATCH($B20,$B$12:$B$15,0))),"NA") -> 5.9904452 | J20: =IFERROR(IF(INDEX(J$7:J$10,MATCH($B20,$B$7:$B$10,0))/INDEX(J$12:J$15,MATCH($B20,$B$12:$B$15,0))<0,"NM",INDEX(J$7:J$10,MATCH($B20,$B$7:$B$10,0))/INDEX(J$12:J$15,MATCH($B20,$B$12:$B$15,0))),"NA") -> 8.3854928 | K20: =IFERROR(IF(INDEX(K$7:K$10,MATCH($B20,$B$7:$B$10,0))/INDEX(J$12:J$15,MATCH($B20,$B$12:$B$15,0))<0,"NM",INDEX(K$7:K$10,MATCH($B20,$B$7:$B$10,0))/INDEX(J$12:J$15,MATCH($B20,$B$12:$B$15,0))),"NA") -> 72.190632 | M20: =IFERROR(IF(INDEX(M$7:M$10,MATCH($B20,$B$7:$B$10,0))/INDEX(M$12:M$15,MATCH($B20,$B$12:$B$15,0))<0,"NM",INDEX(M$7:M$10,MATCH($B20,$B$7:$B$10,0))/INDEX(M$12:M$15,MATCH($B20,$B$12:$B$15,0))),"NA") -> 98.565805 | N20: =IFERROR(IF(INDEX(N$7:N$10,MATCH($B20,$B$7:$B$10,0))/INDEX(M$12:M$15,MATCH($B20,$B$12:$B$15,0))<0,"NM",INDEX(N$7:N$10,MATCH($B20,$B$7:$B$10,0))/INDEX(M$12:M$15,MATCH($B20,$B$12:$B$15,0))),"NA") -> 442.10749 | Q20: =IFERROR(AVERAGE(G20,J20,M20),"NA") -> 35.995689 | R20: =IFERROR(AVERAGE(H20,K20,N20),"NA") -> 173.42952
B21: Average | D21: =IFERROR(AVERAGE(D17:D20),"NA") -> 35.526161 | E21: =IFERROR(AVERAGE(E17:E20),"NA") -> 180.57669 | G21: =IFERROR(AVERAGE(G17:G20),"NA") -> 9.6467397 | H21: =IFERROR(AVERAGE(H17:H20),"NA") -> 42.254046 | J21: =IFERROR(AVERAGE(J17:J20),"NA") -> 26.50395 | K21: =IFERROR(AVERAGE(K17:K20),"NA") -> 115.94942 | M21: =IFERROR(AVERAGE(M17:M20),"NA") -> 144.20147 | N21: =IFERROR(AVERAGE(N17:N20),"NA") -> 653.0384 | Q21: =IFERROR(AVERAGE(Q17:Q20),"NA") -> 52.837468 | R21: =IFERROR(AVERAGE(R17:R20),"NA") -> 235.13275
A23: Discount Applied | G23: 0.1 | J23: 0.2 | M23: 0.5 | P23: =AVERAGE(G21*(1-G23),J21*(1-J23),M21*(1-M23)) -> 33.99532 | Q23: =AVERAGE(G21*(1-$G$23),M21*(1-$M$23),J21*(1-$J$23)) -> 33.99532 | R23: =AVERAGE(H21*(1-$G$23),N21*(1-$M$23),K21*(1-$J$23)) -> 152.43579
A25: Using Historical Averages
A26: Historical Peer Group | D26: =AVERAGE($Q$23:$R$23) -> 93.215556
A27: Historical Target Firm | D27: =AVERAGE($D$21:$E$21) -> 108.05142
A29: Average Market Cap/Sales | D29: =AVERAGE(D27,D26) -> 100.63349
A30: x Projected Forward Sales | D30: =Financials!J11 -> 51863 | J30: =360000/2862 -> 125.78616
A31: Relative Market Cap | D31: =D29*D30 -> 5219154.7
A32: - Projected Interest-Bearing Debt | D32: =Financials!J200+Financials!J205+Financials!J210 -> 0
A33: + Projected Cash and Cash Equivalents | D33: =Financials!J52 -> 210462.67
A34: Relative Market Value of Equity | D34: =D31-D32+D33 -> 5429617.4
A36: Relative EV/Sales Target Price | D36: =D31/Assumptions!B25 -> 38.980915
A38: Helpful Notes:
A39: Check the note in the cell "Historical Relative" on the top left corner in Yellow
A40: Be sure to check your data for outliers that may be skewing the results of the model and delete them.
A41: If you are not sure about a value, consult your SM

Sheet EV-Sales Multiples
A1: EV/Sales Market Multiples Model
A3: Peer Group: | D3: =Comp_Name -> Nu Scale | G3: FCEL | J3: EOSE | M3: HYLN | Q3: Peer Group Average
B5: Year | D5: Low | E5: High | G5: Low | H5: High | J5: Low | K5: High | M5: Low | N5: High | Q5: Low | R5: High
A7: Enterprise Value (EV) | B7: {=INDEX(Annual_Periods,1)} -> 44560 | D7: 244909.7 | E7: 1030960 | G7: 719133.9 | H7: 9111575.1 | J7: 287919 | K7: 1393447.4 | M7: 584309 | N7: 2613261 | Q7: =AVERAGE(D7, G7, J7, M7) -> 459067.9 | R7: =AVERAGE(E7, H7, K7, N7) -> 3537310.9
B8: =EOMONTH(B7,12) -> 44926 | D8: 271110 | E8: 3302340 | G8: 841910.5 | H8: 3849752 | J8: 68051.2 | K8: 415183.2 | M8: 14219.99 | N8: 719820 | Q8: =AVERAGE(D8, G8, J8, M8) -> 298822.92 | R8: =AVERAGE(E8, H8, K8, N8) -> 2071773.8
B9: =EOMONTH(B8,12) -> 45291 | D9: 437770 | E9: 2441900 | G9: 189037.4 | H9: 1444709.1 | J9: 269035.2 | K9: 803856.7 | M9: -124089.9 | N9: 366241 | Q9: =AVERAGE(D9, G9, J9, M9) -> 192938.18 | R9: =AVERAGE(E9, H9, K9, N9) -> 1264176.7
B10: =EOMONTH(B9,12) -> 45657 | D10: 359700 | E10: 7493900 | G10: 45265.3 | H10: 671720.6 | J10: 270284.2 | K10: 1793949.1 | M10: -680.32 | N10: 522706.2 | Q10: =AVERAGE(D10, G10, J10, M10) -> 168642.3 | R10: =AVERAGE(E10, H10, K10, N10) -> 2620569
A12: Annual Sales | B12: =B7 -> 44560 | D12: =Financials!F11 -> 2862 | G12: 69585 | J12: 4598 | M12: 200 | Q12: =AVERAGE(D12, G12, J12, M12) -> 19311.25
B13: =B8 -> 44926 | D13: =Financials!G11 -> 11804 | G13: 130484 | J13: 17924 | M13: 2106 | Q13: =AVERAGE(D13, G13, J13, M13) -> 40579.5
B14: =B9 -> 45291 | D14: =Financials!H11 -> 22810 | G14: 123394 | J14: 16378 | M14: 672 | Q14: =AVERAGE(D14, G14, J14, M14) -> 40813.5
B15: =B10 -> 45657 | D15: =Financials!I11 -> 37045 | G15: 112132 | J15: 15606 | M15: 1509 | Q15: =AVERAGE(D15, G15, J15, M15) -> 41573
A17: EV/Sales Ratio | B17: =B7 -> 44560 | D17: =IFERROR(IF(INDEX(D$7:D$10,MATCH($B17,$B$7:$B$10,0))/INDEX(D$12:D$15,MATCH($B17,$B$12:$B$15,0))<0,"NM",INDEX(D$7:D$10,MATCH($B17,$B$7:$B$10,0))/INDEX(D$12:D$15,MATCH($B17,$B$12:$B$15,0))),"NA") -> 85.572921 | E17: =IFERROR(IF(INDEX(E$7:E$10,MATCH($B17,$B$7:$B$10,0))/INDEX(D$12:D$15,MATCH($B17,$B$12:$B$15,0))<0,"NM",INDEX(E$7:E$10,MATCH($B17,$B$7:$B$10,0))/INDEX(D$12:D$15,MATCH($B17,$B$12:$B$15,0))),"NA") -> 360.22362 | G17: =IFERROR(IF(INDEX(G$7:G$10,MATCH($B17,$B$7:$B$10,0))/INDEX(G$12:G$15,MATCH($B17,$B$12:$B$15,0))<0,"NM",INDEX(G$7:G$10,MATCH($B17,$B$7:$B$10,0))/INDEX(G$12:G$15,MATCH($B17,$B$12:$B$15,0))),"NA") -> 10.334611 | H17: =IFERROR(IF(INDEX(H$7:H$10,MATCH($B17,$B$7:$B$10,0))/INDEX(G$12:G$15,MATCH($B17,$B$12:$B$15,0))<0,"NM",INDEX(H$7:H$10,MATCH($B17,$B$7:$B$10,0))/INDEX(G$12:G$15,MATCH($B17,$B$12:$B$15,0))),"NA") -> 130.94166 | J17: =IFERROR(IF(INDEX(J$7:J$10,MATCH($B17,$B$7:$B$10,0))/INDEX(J$12:J$15,MATCH($B17,$B$12:$B$15,0))<0,"NM",INDEX(J$7:J$10,MATCH($B17,$B$7:$B$10,0))/INDEX(J$12:J$15,MATCH($B17,$B$12:$B$15,0))),"NA") -> 62.618312 | K17: =IFERROR(IF(INDEX(K$7:K$10,MATCH($B17,$B$7:$B$10,0))/INDEX(J$12:J$15,MATCH($B17,$B$12:$B$15,0))<0,"NM",INDEX(K$7:K$10,MATCH($B17,$B$7:$B$10,0))/INDEX(J$12:J$15,MATCH($B17,$B$12:$B$15,0))),"NA") -> 303.05511 | M17: NM | N17: NM | Q17: =IFERROR(AVERAGE(G17,J17,M17),"NA") -> 36.476462 | R17: =IFERROR(AVERAGE(H17,K17,N17),"NA") -> 216.99838
B18: =B8 -> 44926 | D18: =IFERROR(IF(INDEX(D$7:D$10,MATCH($B18,$B$7:$B$10,0))/INDEX(D$12:D$15,MATCH($B18,$B$12:$B$15,0))<0,"NM",INDEX(D$7:D$10,MATCH($B18,$B$7:$B$10,0))/INDEX(D$12:D$15,MATCH($B18,$B$12:$B$15,0))),"NA") -> 22.967638 | E18: =IFERROR(IF(INDEX(E$7:E$10,MATCH($B18,$B$7:$B$10,0))/INDEX(D$12:D$15,MATCH($B18,$B$12:$B$15,0))<0,"NM",INDEX(E$7:E$10,MATCH($B18,$B$7:$B$10,0))/INDEX(D$12:D$15,MATCH($B18,$B$12:$B$15,0))),"NA") -> 279.76449 | G18: =IFERROR(IF(INDEX(G$7:G$10,MATCH($B18,$B$7:$B$10,0))/INDEX(G$12:G$15,MATCH($B18,$B$12:$B$15,0))<0,"NM",INDEX(G$7:G$10,MATCH($B18,$B$7:$B$10,0))/INDEX(G$12:G$15,MATCH($B18,$B$12:$B$15,0))),"NA") -> 6.4522125 | H18: =IFERROR(IF(INDEX(H$7:H$10,MATCH($B18,$B$7:$B$10,0))/INDEX(G$12:G$15,MATCH($B18,$B$12:$B$15,0))<0,"NM",INDEX(H$7:H$10,MATCH($B18,$B$7:$B$10,0))/INDEX(G$12:G$15,MATCH($B18,$B$12:$B$15,0))),"NA") -> 29.503633 | J18: =IFERROR(IF(INDEX(J$7:J$10,MATCH($B18,$B$7:$B$10,0))/INDEX(J$12:J$15,MATCH($B18,$B$12:$B$15,0))<0,"NM",INDEX(J$7:J$10,MATCH($B18,$B$7:$B$10,0))/INDEX(J$12:J$15,MATCH($B18,$B$12:$B$15,0))),"NA") -> 3.7966525 | K18: =IFERROR(IF(INDEX(K$7:K$10,MATCH($B18,$B$7:$B$10,0))/INDEX(J$12:J$15,MATCH($B18,$B$12:$B$15,0))<0,"NM",INDEX(K$7:K$10,MATCH($B18,$B$7:$B$10,0))/INDEX(J$12:J$15,MATCH($B18,$B$12:$B$15,0))),"NA") -> 23.163535 | M18: =IFERROR(IF(INDEX(M$7:M$10,MATCH($B18,$B$7:$B$10,0))/INDEX(M$12:M$15,MATCH($B18,$B$12:$B$15,0))<0,"NM",INDEX(M$7:M$10,MATCH($B18,$B$7:$B$10,0))/INDEX(M$12:M$15,MATCH($B18,$B$12:$B$15,0))),"NA") -> 6.752132 | N18: =IFERROR(IF(INDEX(N$7:N$10,MATCH($B18,$B$7:$B$10,0))/INDEX(M$12:M$15,MATCH($B18,$B$12:$B$15,0))<0,"NM",INDEX(N$7:N$10,MATCH($B18,$B$7:$B$10,0))/INDEX(M$12:M$15,MATCH($B18,$B$12:$B$15,0))),"NA") -> 341.79487 | Q18: =IFERROR(AVERAGE(G18,J18,M18),"NA") -> 5.666999 | R18: =IFERROR(AVERAGE(H18,K18,N18),"NA") -> 131.48735
B19: =B9 -> 45291 | D19: =IFERROR(IF(INDEX(D$7:D$10,MATCH($B19,$B$7:$B$10,0))/INDEX(D$12:D$15,MATCH($B19,$B$12:$B$15,0))<0,"NM",INDEX(D$7:D$10,MATCH($B19,$B$7:$B$10,0))/INDEX(D$12:D$15,MATCH($B19,$B$12:$B$15,0))),"NA") -> 19.192021 | E19: =IFERROR(IF(INDEX(E$7:E$10,MATCH($B19,$B$7:$B$10,0))/INDEX(D$12:D$15,MATCH($B19,$B$12:$B$15,0))<0,"NM",INDEX(E$7:E$10,MATCH($B19,$B$7:$B$10,0))/INDEX(D$12:D$15,MATCH($B19,$B$12:$B$15,0))),"NA") -> 107.05392 | G19: =IFERROR(IF(INDEX(G$7:G$10,MATCH($B19,$B$7:$B$10,0))/INDEX(G$12:G$15,MATCH($B19,$B$12:$B$15,0))<0,"NM",INDEX(G$7:G$10,MATCH($B19,$B$7:$B$10,0))/INDEX(G$12:G$15,MATCH($B19,$B$12:$B$15,0))),"NA") -> 1.5319821 | H19: =IFERROR(IF(INDEX(H$7:H$10,MATCH($B19,$B$7:$B$10,0))/INDEX(G$12:G$15,MATCH($B19,$B$12:$B$15,0))<0,"NM",INDEX(H$7:H$10,MATCH($B19,$B$7:$B$10,0))/INDEX(G$12:G$15,MATCH($B19,$B$12:$B$15,0))),"NA") -> 11.708098 | J19: =IFERROR(IF(INDEX(J$7:J$10,MATCH($B19,$B$7:$B$10,0))/INDEX(J$12:J$15,MATCH($B19,$B$12:$B$15,0))<0,"NM",INDEX(J$7:J$10,MATCH($B19,$B$7:$B$10,0))/INDEX(J$12:J$15,MATCH($B19,$B$12:$B$15,0))),"NA") -> 16.426621 | K19: =IFERROR(IF(INDEX(K$7:K$10,MATCH($B19,$B$7:$B$10,0))/INDEX(J$12:J$15,MATCH($B19,$B$12:$B$15,0))<0,"NM",INDEX(K$7:K$10,MATCH($B19,$B$7:$B$10,0))/INDEX(J$12:J$15,MATCH($B19,$B$12:$B$15,0))),"NA") -> 49.081493 | M19: =IFERROR(IF(INDEX(M$7:M$10,MATCH($B19,$B$7:$B$10,0))/INDEX(M$12:M$15,MATCH($B19,$B$12:$B$15,0))<0,"NM",INDEX(M$7:M$10,MATCH($B19,$B$7:$B$10,0))/INDEX(M$12:M$15,MATCH($B19,$B$12:$B$15,0))),"NA") -> NM | N19: =IFERROR(IF(INDEX(N$7:N$10,MATCH($B19,$B$7:$B$10,0))/INDEX(M$12:M$15,MATCH($B19,$B$12:$B$15,0))<0,"NM",INDEX(N$7:N$10,MATCH($B19,$B$7:$B$10,0))/INDEX(M$12:M$15,MATCH($B19,$B$12:$B$15,0))),"NA") -> 545.00149 | Q19: =IFERROR(AVERAGE(G19,J19,M19),"NA") -> 8.9793016 | R19: =IFERROR(AVERAGE(H19,K19,N19),"NA") -> 201.93036
B20: =B10 -> 45657 | D20: =IFERROR(IF(INDEX(D$7:D$10,MATCH($B20,$B$7:$B$10,0))/INDEX(D$12:D$15,MATCH($B20,$B$12:$B$15,0))<0,"NM",INDEX(D$7:D$10,MATCH($B20,$B$7:$B$10,0))/INDEX(D$12:D$15,MATCH($B20,$B$12:$B$15,0))),"NA") -> 9.7098124 | E20: =IFERROR(IF(INDEX(E$7:E$10,MATCH($B20,$B$7:$B$10,0))/INDEX(D$12:D$15,MATCH($B20,$B$12:$B$15,0))<0,"NM",INDEX(E$7:E$10,MATCH($B20,$B$7:$B$10,0))/INDEX(D$12:D$15,MATCH($B20,$B$12:$B$15,0))),"NA") -> 202.29181 | G20: =IFERROR(IF(INDEX(G$7:G$10,MATCH($B20,$B$7:$B$10,0))/INDEX(G$12:G$15,MATCH($B20,$B$12:$B$15,0))<0,"NM",INDEX(G$7:G$10,MATCH($B20,$B$7:$B$10,0))/INDEX(G$12:G$15,MATCH($B20,$B$12:$B$15,0))),"NA") -> 0.4036787 | H20: =IFERROR(IF(INDEX(H$7:H$10,MATCH($B20,$B$7:$B$10,0))/INDEX(G$12:G$15,MATCH($B20,$B$12:$B$15,0))<0,"NM",INDEX(H$7:H$10,MATCH($B20,$B$7:$B$10,0))/INDEX(G$12:G$15,MATCH($B20,$B$12:$B$15,0))),"NA") -> 5.9904452 | J20: =IFERROR(IF(INDEX(J$7:J$10,MATCH($B20,$B$7:$B$10,0))/INDEX(J$12:J$15,MATCH($B20,$B$12:$B$15,0))<0,"NM",INDEX(J$7:J$10,MATCH($B20,$B$7:$B$10,0))/INDEX(J$12:J$15,MATCH($B20,$B$12:$B$15,0))),"NA") -> 17.319249 | K20: =IFERROR(IF(INDEX(K$7:K$10,MATCH($B20,$B$7:$B$10,0))/INDEX(J$12:J$15,MATCH($B20,$B$12:$B$15,0))<0,"NM",INDEX(K$7:K$10,MATCH($B20,$B$7:$B$10,0))/INDEX(J$12:J$15,MATCH($B20,$B$12:$B$15,0))),"NA") -> 114.95252 | M20: =IFERROR(IF(INDEX(M$7:M$10,MATCH($B20,$B$7:$B$10,0))/INDEX(M$12:M$15,MATCH($B20,$B$12:$B$15,0))<0,"NM",INDEX(M$7:M$10,MATCH($B20,$B$7:$B$10,0))/INDEX(M$12:M$15,MATCH($B20,$B$12:$B$15,0))),"NA") -> NM | N20: =IFERROR(IF(INDEX(N$7:N$10,MATCH($B20,$B$7:$B$10,0))/INDEX(M$12:M$15,MATCH($B20,$B$12:$B$15,0))<0,"NM",INDEX(N$7:N$10,MATCH($B20,$B$7:$B$10,0))/INDEX(M$12:M$15,MATCH($B20,$B$12:$B$15,0))),"NA") -> 346.39245 | Q20: =IFERROR(AVERAGE(G20,J20,M20),"NA") -> 8.8614639 | R20: =IFERROR(AVERAGE(H20,K20,N20),"NA") -> 155.77847
B21: Average | D21: =IFERROR(AVERAGE(D17:D20),"NA") -> 34.360598 | E21: =IFERROR(AVERAGE(E17:E20),"NA") -> 237.33346 | G21: =IFERROR(AVERAGE(G17:G20),"NA") -> 4.6806211 | H21: =IFERROR(AVERAGE(H17:H20),"NA") -> 44.535958 | J21: =IFERROR(AVERAGE(J17:J20),"NA") -> 25.040209 | K21: =IFERROR(AVERAGE(K17:K20),"NA") -> 122.56317 | M21: =IFERROR(AVERAGE(M17:M20),"NA") -> 6.752132 | N21: =IFERROR(AVERAGE(N17:N20),"NA") -> 411.06294 | Q21: =IFERROR(AVERAGE(Q17:Q20),"NA") -> 14.996057 | R21: =IFERROR(AVERAGE(R17:R20),"NA") -> 176.54864
A23: Discount Applied | G23: 0.25 | J23: 0 | M23: 0.3 | P23: =AVERAGE(G21*(1-G23),J21*(1-J23),M21*(1-M23)) -> 11.092389 | Q23: =AVERAGE(G21*(1-$G$23),M21*(1-$M$23),J21*(1-$J$23)) -> 11.092389 | R23: =AVERAGE(H21*(1-$G$23),N21*(1-$M$23),K21*(1-$J$23)) -> 147.90306
A25: Using Historical Averages
A26: Historical Peer Group | D26: =AVERAGE($Q$23:$R$23) -> 79.497726
A27: Historical Target Firm | D27: =AVERAGE($D$21:$E$21) -> 135.84703
A29: Average EV/Sales | D29: =AVERAGE(D27,D26) -> 107.67238
A30: x Projected Forward Sales | D30: =Financials!J11 -> 51863
A31: Relative EV | D31: =D29*D30 -> 5584212.5
A32: - Projected Interest-Bearing Debt | D32: =Financials!J200+Financials!J205+Financials!J210 -> 0
A33: + Projected Cash and Cash Equivalents | D33: =Financials!J52 -> 210462.67
A34: Relative Market Value of Equity | D34: =D31-D32+D33 -> 5794675.2
A36: Relative EV/Sales Target Price | D36: =D34/Assumptions!B25 -> 43.279372
A38: Helpful Notes:
A39: Check the note in the cell "Historical Relative" on the top left corner in Yellow
A40: Be sure to check your data for outliers that may be skewing the results of the model and delete them.
A41: If you are not sure about a value, consult your SM

Sheet Precedent Transaction Multiple
A1: Transaction Multiples ( You will need to shortlist companies in the similar industry and have the same operations. Then shortlist potential peers based on geographic location, mkt cap etc)
A3: Purchased Companies | B3: EV/Revenue LTM
A4: Peer 1
A5: Peer 2
A6: Peer 3
A7: Peer 4
A8: Peer 5
A9: Peer 6
A10: Peer 7
A11: Peer 8
A13: Methodology | B13: Value
A14: Average EV/Revenue | B14: =IFERROR(AVERAGE(B4:B11), "N/A") -> N/A
A15: Projected 12M revenue | B15: =Financials!J11 -> 51863
A16: Implied Enterprise Value | B16: =IFERROR((B15*B14),"N/A") -> N/A
A17: Net Financial Claims | B17: =SUMIF(BS_Start:BS_End,"Cash",OFFSET(BS_Start,0,MATCH(Financials!J6,Financials!$6:$6,0)-COLUMN(BS_Start))) - SUMIF(BS_Start:BS_End,"FC",OFFSET(BS_Start,0,MATCH(Financials!J6,Financials!$6:$6,0)-COLUMN(BS_Start))) -> 250462.67
A18: Equity Value | B18: =B16+B17 -> #VALUE!
A19: Shares Outstanding | B19: =Shares_Out -> 133890
A20: Forward Share Price(Fair Value) | B20: =B18/B19 -> #VALUE!

Sheet IS Summary
A1: ="Financials Summary ($"&Scale_Symbol&")" -> Financials Summary ($K) | N1: Automated Page for Reference Only
A2: ="Sales Growth Assumption: "&TEXT(#REF!,"0.0%") -> #REF! | B2: Historic | F2: Projected
A3: Fiscal Year: | B3: {=Annual_Periods} -> 44560 | C3: 44926 | D3: 45291 | E3: 45657 | F3: 46022 | G3: 46387 | H3: 46752 | I3: 47118 | J3: 47483
A5: Gross Shipments | B5: =INDEX(#REF!,MATCH(B$3,#REF!,0)) -> #REF! | C5: =INDEX(#REF!,MATCH(C$3,#REF!,0)) -> #REF! | D5: =INDEX(#REF!,MATCH(D$3,#REF!,0)) -> #REF! | E5: =INDEX(#REF!,MATCH(E$3,#REF!,0)) -> #REF! | F5: =INDEX(#REF!,MATCH(F$3,#REF!,0)) -> #REF! | G5: =INDEX(#REF!,MATCH(G$3,#REF!,0)) -> #REF! | H5: =INDEX(#REF!,MATCH(H$3,#REF!,0)) -> #REF! | I5: =INDEX(#REF!,MATCH(I$3,#REF!,0)) -> #REF! | J5: =INDEX(#REF!,MATCH(J$3,#REF!,0)) -> #REF! | L5: =_xlfn.RRI(COUNT(OFFSET($A$3,0,1):OFFSET($L$3,0,-1))-1,$B5,$F5) -> #REF!
A6: Less: Deductions & Allowances | B6: =INDEX(#REF!,MATCH(B$3,#REF!,0)) -> #REF! | C6: =INDEX(#REF!,MATCH(C$3,#REF!,0)) -> #REF! | D6: =INDEX(#REF!,MATCH(D$3,#REF!,0)) -> #REF! | E6: =INDEX(#REF!,MATCH(E$3,#REF!,0)) -> #REF! | F6: =INDEX(#REF!,MATCH(F$3,#REF!,0)) -> #REF! | G6: =INDEX(#REF!,MATCH(G$3,#REF!,0)) -> #REF! | H6: =INDEX(#REF!,MATCH(H$3,#REF!,0)) -> #REF! | I6: =INDEX(#REF!,MATCH(I$3,#REF!,0)) -> #REF! | J6: =INDEX(#REF!,MATCH(J$3,#REF!,0)) -> #REF!
A7: Net Sales | B7: =INDEX(Financials!$11:$11,MATCH(B$3,Financials!$6:$6,0)) -> 2862 | C7: =INDEX(Financials!$11:$11,MATCH(C$3,Financials!$6:$6,0)) -> 11804 | D7: =INDEX(Financials!$11:$11,MATCH(D$3,Financials!$6:$6,0)) -> 22810 | E7: =INDEX(Financials!$11:$11,MATCH(E$3,Financials!$6:$6,0)) -> 37045 | F7: =INDEX(Financials!$11:$11,MATCH(F$3,Financials!$6:$6,0)) -> 51863 | G7: =INDEX(Financials!$11:$11,MATCH(G$3,Financials!$6:$6,0)) -> 82980.8 | H7: =INDEX(Financials!$11:$11,MATCH(H$3,Financials!$6:$6,0)) -> 165961.6 | I7: =INDEX(Financials!$11:$11,MATCH(I$3,Financials!$6:$6,0)) -> 365115.52 | J7: =INDEX(Financials!$11:$11,MATCH(J$3,Financials!$6:$6,0)) -> 657207.94 | L7: =_xlfn.RRI(5,E7,J7) -> 0.77743873
A8: Less: COGS | B8: =INDEX(Financials!$16:$16,MATCH(B$3,Financials!$6:$6,0)) -> -1770 | C8: =INDEX(Financials!$16:$16,MATCH(C$3,Financials!$6:$6,0)) -> -7317 | D8: =INDEX(Financials!$16:$16,MATCH(D$3,Financials!$6:$6,0)) -> -18961 | E8: =INDEX(Financials!$16:$16,MATCH(E$3,Financials!$6:$6,0)) -> -4937 | F8: =INDEX(Financials!$16:$16,MATCH(F$3,Financials!$6:$6,0)) -> -10372.6 | G8: =INDEX(Financials!$16:$16,MATCH(G$3,Financials!$6:$6,0)) -> -20745.2 | H8: =INDEX(Financials!$16:$16,MATCH(H$3,Financials!$6:$6,0)) -> -41490.4 | I8: =INDEX(Financials!$16:$16,MATCH(I$3,Financials!$6:$6,0)) -> -109534.66 | J8: =INDEX(Financials!$16:$16,MATCH(J$3,Financials!$6:$6,0)) -> -230022.78
A9: Gross Profit | B9: =B7+B8 -> 1092 | C9: =C7+C8 -> 4487 | D9: =D7+D8 -> 3849 | E9: =E7+E8 -> 32108 | F9: =F7+F8 -> 41490.4 | G9: =G7+G8 -> 62235.6 | H9: =H7+H8 -> 124471.2 | I9: =I7+I8 -> 255580.86 | J9: =J7+J8 -> 427185.16
A10: Gross Margin % | B10: =IFERROR(B9/B$7,"NA") -> 0.38155136 | C10: =IFERROR(C9/C$7,"NA") -> 0.38012538 | D10: =IFERROR(D9/D$7,"NA") -> 0.16874178 | E10: =IFERROR(E9/E$7,"NA") -> 0.86672965 | F10: =IFERROR(F9/F$7,"NA") -> 0.8 | G10: =IFERROR(G9/G$7,"NA") -> 0.75 | H10: =IFERROR(H9/H$7,"NA") -> 0.75 | I10: =IFERROR(I9/I$7,"NA") -> 0.7 | J10: =IFERROR(J9/J$7,"NA") -> 0.65
A12: Less: Operating Expense | B12: =-INDEX(Financials!$27:$27,MATCH(B$3,Financials!$6:$6,0)) -> -175392 | C12: =-INDEX(Financials!$27:$27,MATCH(C$3,Financials!$6:$6,0)) -> -234482 | D12: =-INDEX(Financials!$27:$27,MATCH(D$3,Financials!$6:$6,0)) -> -279414 | E12: =-INDEX(Financials!$27:$27,MATCH(E$3,Financials!$6:$6,0)) -> -170833 | F12: =-INDEX(Financials!$27:$27,MATCH(F$3,Financials!$6:$6,0)) -> -178927.35 | G12: =-INDEX(Financials!$27:$27,MATCH(G$3,Financials!$6:$6,0)) -> -186706.8 | H12: =-INDEX(Financials!$27:$27,MATCH(H$3,Financials!$6:$6,0)) -> -190855.84 | I12: =-INDEX(Financials!$27:$27,MATCH(I$3,Financials!$6:$6,0)) -> -197162.38 | J12: =-INDEX(Financials!$27:$27,MATCH(J$3,Financials!$6:$6,0)) -> -295743.57
A13: Operating Income (EBIT) | B13: =B9+B12 -> -174300 | C13: =C9+C12 -> -229995 | D13: =D9+D12 -> -275565 | E13: =E9+E12 -> -138725 | F13: =F9+F12 -> -137436.95 | G13: =G9+G12 -> -124471.2 | H13: =H9+H12 -> -66384.64 | I13: =I9+I12 -> 58418.483 | J13: =J9+J12 -> 131441.59
A14: Operating Margin % | B14: =IFERROR(B13/B$7,"NA") -> -60.901468 | C14: =IFERROR(C13/C$7,"NA") -> -19.484497 | D14: =IFERROR(D13/D$7,"NA") -> -12.080886 | E14: =IFERROR(E13/E$7,"NA") -> -3.7447699 | F14: =IFERROR(F13/F$7,"NA") -> -2.65 | G14: =IFERROR(G13/G$7,"NA") -> -1.5 | H14: =IFERROR(H13/H$7,"NA") -> -0.4 | I14: =IFERROR(I13/I$7,"NA") -> 0.16 | J14: =IFERROR(J13/J$7,"NA") -> 0.2
A16: Net Income | B16: =INDEX(Financials!$40:$40,MATCH(B$3,Financials!$6:$6,0)) -> -176015 | C16: =INDEX(Financials!$40:$40,MATCH(C$3,Financials!$6:$6,0)) -> -226235 | D16: =INDEX(Financials!$40:$40,MATCH(D$3,Financials!$6:$6,0)) -> -264773 | E16: =INDEX(Financials!$40:$40,MATCH(E$3,Financials!$6:$6,0)) -> -138725 | F16: =INDEX(Financials!$40:$40,MATCH(F$3,Financials!$6:$6,0)) -> -137436.95 | G16: =INDEX(Financials!$40:$40,MATCH(G$3,Financials!$6:$6,0)) -> -124471.2 | H16: =INDEX(Financials!$40:$40,MATCH(H$3,Financials!$6:$6,0)) -> -66384.64 | I16: =INDEX(Financials!$40:$40,MATCH(I$3,Financials!$6:$6,0)) -> 58418.483 | J16: =INDEX(Financials!$40:$40,MATCH(J$3,Financials!$6:$6,0)) -> 131441.59
A17: Profit Margin % | B17: =IFERROR(B16/B$7,"NA") -> -61.500699 | C17: =IFERROR(C16/C$7,"NA") -> -19.165961 | D17: =IFERROR(D16/D$7,"NA") -> -11.60776 | E17: =IFERROR(E16/E$7,"NA") -> -3.7447699 | F17: =IFERROR(F16/F$7,"NA") -> -2.65 | G17: =IFERROR(G16/G$7,"NA") -> -1.5 | H17: =IFERROR(H16/H$7,"NA") -> -0.4 | I17: =IFERROR(I16/I$7,"NA") -> 0.16 | J17: =IFERROR(J16/J$7,"NA") -> 0.2
